Program_Delay_Timer/delay_timer.sv
module delay_timer #(
    parameter int WEIGHT_BIT_WIDTH = 8
) (
    input clk,
    input rst_n,
    input trigger_in,
    input mode_a,
    input mode_b,

    input [WEIGHT_BIT_WIDTH-1:0] weighted_bits,

    output reg delay_out_n
);

    reg [WEIGHT_BIT_WIDTH-1:0] pulse_width, delay;
    reg [WEIGHT_BIT_WIDTH-1:0] timer = 0;

    reg trigger_d1  = 0;
    reg trigger_d2  = 0;
    reg timer_start     = 0;
    reg out_low         = 0;

    reg [1:0] delay_mode;

    reg reset_timer_d0 = 0;
    reg reset_timer_d1 = 0;
    reg reset_timer_d2 = 0;
    reg reset_d1       = 0;
    reg reset_d2       = 0;

    wire trigger_rise, trigger_fall;
    wire reset_timer_d3, reset_d0;
    wire timer_clr_d0, timer_clr_2, timer_clr_d3;

    always @(posedge clk or negedge rst_n) begin
        if (~rst_n) begin
            trigger_d1     <= 0;
            trigger_d2     <= 0;
            reset_timer_d1 <= 0;
            reset_timer_d2 <= 0;
            reset_d1       <= 0;
            reset_d2       <= 0;
        end else begin
            trigger_d1     <= trigger_in;
            trigger_d2     <= trigger_d1;
            reset_timer_d1 <= reset_timer_d0;
            reset_timer_d2 <= reset_timer_d1;
            reset_d1       <= rst_n;
            reset_d2       <= reset_d1;
        end
    end

    // Identify 0 -> 1 transition on trigger signal
    assign trigger_rise = trigger_d1 & (~trigger_d2);
    assign trigger_fall = trigger_d2 & (~trigger_d1);

    assign reset_timer_d3 = reset_timer_d1 && (~reset_timer_d2);
    assign reset_d0       = reset_d2 & (~reset_d1);

    // Sample mode & weighted bits
    always @(trigger_rise, trigger_fall, mode_a, mode_b, weighted_bits) begin
        if (trigger_fall || trigger_rise) begin
            pulse_width = weighted_bits;
            delay       = (2*weighted_bits + 1)/2;
            delay_mode  = {mode_a, mode_b};
        end
    end

    // Delay modes
    always @(delay_mode, rst_n, trigger_rise, trigger_fall, timer, trigger_in, pulse_width, delay, reset_d0) begin
        case(delay_mode)
            2'b00: // One-shot mode
                begin
                    if (rst_n) begin
                        out_low        <= 0;
                        timer_start    <= 0;
                        reset_timer_d0 <= 0;
                    end else if (trigger_rise) begin
                        out_low        <= 1;
                        timer_start    <= 1;
                        reset_timer_d0 <= 1;
                    end else if (timer >= pulse_width) begin
                        out_low        <= 0;
                        timer_start    <= 0;
                        reset_timer_d0 <= 1;
                    end
                end
            2'b01: // Delayed operation mode
                begin
                    if (rst_n) begin
                        out_low        <= 0;
                        timer_start    <= 0;
                        reset_timer_d0 <= 1;
                    end else if (reset_d0 && trigger_in) begin
                        timer_start    <= 1;
                        reset_timer_d0 <= 0;
                    end else if (trigger_rise) begin
                        timer_start    <= 1;
                        reset_timer_d0 <= 1;
                    end else if (trigger_fall || ~trigger_in) begin
                        out_low        <= 0;
                        timer_start    <= 0;
                        reset_timer_d0 <= 1;
                    end else if (timer >= delay) begin
                        out_low        <= 1;
                        timer_start    <= 0;
                        reset_timer_d0 <= 1;
                    end
                end
            2'b10: // Delayed release mode
                begin
                    if (rst_n) begin
                        out_low        <= 0;
                        timer_start    <= 0;
                        reset_timer_d0 <= 1;
                    end else if (trigger_rise || trigger_in) begin
                        out_low        <= 1;
                    end else if (trigger_fall) begin
                        timer_start    <= 1;
                        reset_timer_d0 <= 0;
                    end else if (timer >= delay) begin
                        out_low        <= 0;
                        timer_start    <= 0;
                        reset_timer_d0 <= 1;
                    end
                end
            2'b11: // Delayed dual mode
                begin
                    if (rst_n) begin
                        out_low        <= 0;
                        timer_start    <= 0;
                        reset_timer_d0 <= 1;
                    end else if (reset_d0 && trigger_in) begin
                        timer_start    <= 1;
                        reset_timer_d0 <= 0;
                    end else if (trigger_fall || trigger_rise) begin
                        timer_start    <= 1;
                        reset_timer_d0 <= 0;
                    end else if (timer >= delay) begin
                        out_low        <= trigger_in;
                        timer_start    <= 0;
                        reset_timer_d0 <= 1;
                    end
                end
            default: // Default case
                begin
                    out_low        <= 0;
                    timer_start    <= 0;
                    reset_timer_d0 <= 1;
                end
        endcase
    end

    // Timer
    always @(posedge clk or posedge timer_clr_d0) begin
        if (timer_clr_d0) begin
            timer <= 0;
        end else if (timer_start) begin
            timer <= timer + 1;
        end
    end

    assign timer_clr_d0 = reset_timer_d3 || trigger_rise || timer_clr_d3;
    assign timer_clr_d2 = trigger_rise || trigger_fall;
    assign timer_clr_d3 = timer_clr_d2 && (delay_mode == 2'b11);

    // Delay output
    always @(posedge clk or negedge rst_n) begin
        if (rst_n) begin
            delay_out_n <= 0;
        end else begin
            if (out_low) begin
                delay_out_n <= 0;
            end else begin
                delay_out_n <= 1;
            end
        end
    end

endmodule

Program_Delay_Timer/delay_timer_tb.sv
`timescale 1ns/1ps

module delay_timer_tb #() ();

    parameter int WEIGHT_BIT_WIDTH = 8;
    parameter int ENDTIME          = 140000;

    reg clk;
    reg rst_n;
    reg trigger_in;
    reg mode_a;
    reg mode_b;

    reg [WEIGHT_BIT_WIDTH-1:0] weighted_bits;

    wire delay_out_n;

    delay_timer #(
        .WEIGHT_BIT_WIDTH (WEIGHT_BIT_WIDTH)
    ) u_delay_timer (
        .clk           (clk),
        .rst_n         (rst_n),
        .trigger_in    (trigger_in),
        .mode_a        (mode_a),
        .mode_b        (mode_b),
        .weighted_bits (weighted_bits),
        .delay_out_n   (delay_out_n)
    );

    initial begin
        $display("Programmable Digital Delay Timer TB");

        $dumpfile("delay_timer.vcd");
        $dumpvars();
        main;
    end

    task automatic main;
        fork
            clock_gen;
            trigger_rst_gen;
            endsimulation;
        join
    endtask

    task static trigger_rst_gen;
        begin
            // Initialize inputs
            rst_n         = 0;

            #1000;
            weighted_bits = 10;
            mode_a        = 0;
            mode_b        = 0;
            rst_n         = 1;
            trigger_in    = 0;

            #500;
            trigger_in    = 1;

            #15000;
            trigger_in    = 0;

            #15000;
            trigger_in    = 1;

            #2000;
            trigger_in    = 0;

            #2000;
            trigger_in    = 1;

            #2000;
            trigger_in    = 0;

            #20000;
            trigger_in    = 1;

            #30000;
            trigger_in    = 0;

            #2000;
            trigger_in    = 1;

            #2000;
            trigger_in    = 0;

            #4000;
            trigger_in    = 1;

            #10000;
            rst_n         = 0;

            #10000;
            rst_n         = 1;
        end
    endtask

    task static clock_gen;
        begin
            clk = 0;
            forever #500 clk = ~clk;
        end
    endtask

    task static endsimulation;
        begin
            #ENDTIME;
            $display("-------------- THE SIMUALTION FINISHED ------------");
            $finish;
        end
    endtask

endmodule

Program_Delay_Timer/vcd/delay_timer.vcd
$date
	Tue Aug 13 09:08:51 2024
$end
$version
	ModelSim Version 10.5b
$end
$timescale
	1ps
$end

$scope module delay_timer_tb $end
$var parameter 32 ! WEIGHT_BIT_WIDTH $end
$var parameter 32 " ENDTIME $end
$var reg 1 # clk $end
$var reg 1 $ rst_n $end
$var reg 1 % trigger_in $end
$var reg 1 & mode_a $end
$var reg 1 ' mode_b $end
$var reg 8 ( weighted_bits [7:0] $end
$var wire 1 ) delay_out_n $end

$scope task main $end
$upscope $end

$scope task trigger_rst_gen $end
$upscope $end

$scope task clock_gen $end
$upscope $end

$scope task endsimulation $end
$upscope $end

$scope module u_delay_timer $end
$var parameter 32 * WEIGHT_BIT_WIDTH $end
$var wire 1 + clk $end
$var wire 1 , rst_n $end
$var wire 1 - trigger_in $end
$var wire 1 . mode_a $end
$var wire 1 / mode_b $end
$var wire 1 0 weighted_bits [7] $end
$var wire 1 1 weighted_bits [6] $end
$var wire 1 2 weighted_bits [5] $end
$var wire 1 3 weighted_bits [4] $end
$var wire 1 4 weighted_bits [3] $end
$var wire 1 5 weighted_bits [2] $end
$var wire 1 6 weighted_bits [1] $end
$var wire 1 7 weighted_bits [0] $end
$var reg 1 8 delay_out_n $end
$var reg 8 9 pulse_width [7:0] $end
$var reg 8 : delay [7:0] $end
$var reg 8 ; timer [7:0] $end
$var reg 1 < trigger_d1 $end
$var reg 1 = trigger_d2 $end
$var reg 1 > timer_start $end
$var reg 1 ? out_low $end
$var reg 2 @ delay_mode [1:0] $end
$var reg 1 A reset_timer_d0 $end
$var reg 1 B reset_timer_d1 $end
$var reg 1 C reset_timer_d2 $end
$var reg 1 D reset_d1 $end
$var reg 1 E reset_d2 $end
$var wire 1 F trigger_rise $end
$var wire 1 G trigger_fall $end
$var wire 1 H reset_timer_d3 $end
$var wire 1 I reset_d0 $end
$var wire 1 J timer_clr_d0 $end
$var wire 1 K timer_clr_2 $end
$var wire 1 L timer_clr_d3 $end
$var wire 1 M timer_clr_d2 $end
$upscope $end
$upscope $end

$scope begin std $end
$upscope $end
$enddefinitions $end
#0
$dumpvars
0#
0$
x%
x&
x'
bx (
08
bx 9
bx :
b0 ;
0<
0=
0>
0?
bx @
1A
0B
0C
0D
0E
b1000 !
b1111010000100100000 "
b1000 *
0)
0F
0G
0H
0I
0J
zK
0L
0M
0+
0,
x-
x.
x/
x7
x6
x5
x4
x3
x2
x1
x0
$end
#500000
1#
1+
#1000000
b1010 (
0&
0'
1$
0%
0#
07
16
05
14
03
02
01
00
0.
0/
1,
0-
0+
#1500000
1%
1#
1-
1+
1<
1B
1D
18
1H
1)
1F
1J
1M
xL
b1010 9
b1010 :
b0 @
0L
1?
1>
#2000000
0#
0+
#2500000
1#
1+
1=
1C
1E
08
0H
0)
0F
0M
0J
#3000000
0#
0+
#3500000
1#
1+
b1 ;
#4000000
0#
0+
#4500000
1#
1+
b10 ;
#5000000
0#
0+
#5500000
1#
1+
b11 ;
#6000000
0#
0+
#6500000
1#
1+
b100 ;
#7000000
0#
0+
#7500000
1#
1+
b101 ;
#8000000
0#
0+
#8500000
1#
1+
b110 ;
#9000000
0#
0+
#9500000
1#
1+
b111 ;
#10000000
0#
0+
#10500000
1#
1+
b1000 ;
#11000000
0#
0+
#11500000
1#
1+
b1001 ;
#12000000
0#
0+
#12500000
1#
1+
b1010 ;
0?
0>
#13000000
0#
0+
#13500000
1#
1+
18
1)
#14000000
0#
0+
#14500000
1#
1+
#15000000
0#
0+
#15500000
1#
1+
#16000000
0#
0+
#16500000
0%
1#
0-
1+
0<
1G
1M
#17000000
0#
0+
#17500000
1#
1+
0=
0G
0M
#18000000
0#
0+
#18500000
1#
1+
#19000000
0#
0+
#19500000
1#
1+
#20000000
0#
0+
#20500000
1#
1+
#21000000
0#
0+
#21500000
1#
1+
#22000000
0#
0+
#22500000
1#
1+
#23000000
0#
0+
#23500000
1#
1+
#24000000
0#
0+
#24500000
1#
1+
#25000000
0#
0+
#25500000
1#
1+
#26000000
0#
0+
#26500000
1#
1+
#27000000
0#
0+
#27500000
1#
1+
#28000000
0#
0+
#28500000
1#
1+
#29000000
0#
0+
#29500000
1#
1+
#30000000
0#
0+
#30500000
1#
1+
#31000000
0#
0+
#31500000
1%
1#
1-
1+
1<
1F
1M
1J
b0 ;
1?
1>
#32000000
0#
0+
#32500000
1#
1+
1=
08
0)
0F
0M
0J
#33000000
0#
0+
#33500000
0%
1#
0-
1+
0<
b1 ;
1G
1M
#34000000
0#
0+
#34500000
1#
1+
0=
b10 ;
0G
0M
#35000000
0#
0+
#35500000
1%
1#
1-
1+
1<
b11 ;
1F
1M
1J
b0 ;
#36000000
0#
0+
#36500000
1#
1+
1=
0F
0M
0J
#37000000
0#
0+
#37500000
0%
1#
0-
1+
0<
b1 ;
1G
1M
#38000000
0#
0+
#38500000
1#
1+
0=
b10 ;
0G
0M
#39000000
0#
0+
#39500000
1#
1+
b11 ;
#40000000
0#
0+
#40500000
1#
1+
b100 ;
#41000000
0#
0+
#41500000
1#
1+
b101 ;
#42000000
0#
0+
#42500000
1#
1+
b110 ;
#43000000
0#
0+
#43500000
1#
1+
b111 ;
#44000000
0#
0+
#44500000
1#
1+
b1000 ;
#45000000
0#
0+
#45500000
1#
1+
b1001 ;
#46000000
0#
0+
#46500000
1#
1+
b1010 ;
0?
0>
#47000000
0#
0+
#47500000
1#
1+
18
1)
#48000000
0#
0+
#48500000
1#
1+
#49000000
0#
0+
#49500000
1#
1+
#50000000
0#
0+
#50500000
1#
1+
#51000000
0#
0+
#51500000
1#
1+
#52000000
0#
0+
#52500000
1#
1+
#53000000
0#
0+
#53500000
1#
1+
#54000000
0#
0+
#54500000
1#
1+
#55000000
0#
0+
#55500000
1#
1+
#56000000
0#
0+
#56500000
1#
1+
#57000000
0#
0+
#57500000
1%
1#
1-
1+
1<
1F
1M
1J
b0 ;
1?
1>
#58000000
0#
0+
#58500000
1#
1+
1=
08
0)
0F
0M
0J
#59000000
0#
0+
#59500000
1#
1+
b1 ;
#60000000
0#
0+
#60500000
1#
1+
b10 ;
#61000000
0#
0+
#61500000
1#
1+
b11 ;
#62000000
0#
0+
#62500000
1#
1+
b100 ;
#63000000
0#
0+
#63500000
1#
1+
b101 ;
#64000000
0#
0+
#64500000
1#
1+
b110 ;
#65000000
0#
0+
#65500000
1#
1+
b111 ;
#66000000
0#
0+
#66500000
1#
1+
b1000 ;
#67000000
0#
0+
#67500000
1#
1+
b1001 ;
#68000000
0#
0+
#68500000
1#
1+
b1010 ;
0?
0>
#69000000
0#
0+
#69500000
1#
1+
18
1)
#70000000
0#
0+
#70500000
1#
1+
#71000000
0#
0+
#71500000
1#
1+
#72000000
0#
0+
#72500000
1#
1+
#73000000
0#
0+
#73500000
1#
1+
#74000000
0#
0+
#74500000
1#
1+
#75000000
0#
0+
#75500000
1#
1+
#76000000
0#
0+
#76500000
1#
1+
#77000000
0#
0+
#77500000
1#
1+
#78000000
0#
0+
#78500000
1#
1+
#79000000
0#
0+
#79500000
1#
1+
#80000000
0#
0+
#80500000
1#
1+
#81000000
0#
0+
#81500000
1#
1+
#82000000
0#
0+
#82500000
1#
1+
#83000000
0#
0+
#83500000
1#
1+
#84000000
0#
0+
#84500000
1#
1+
#85000000
0#
0+
#85500000
1#
1+
#86000000
0#
0+
#86500000
1#
1+
#87000000
0#
0+
#87500000
0%
1#
0-
1+
0<
1G
1M
#88000000
0#
0+
#88500000
1#
1+
0=
0G
0M
#89000000
0#
0+
#89500000
1%
1#
1-
1+
1<
1F
1M
1J
b0 ;
1?
1>
#90000000
0#
0+
#90500000
1#
1+
1=
08
0)
0F
0M
0J
#91000000
0#
0+
#91500000
0%
1#
0-
1+
0<
b1 ;
1G
1M
#92000000
0#
0+
#92500000
1#
1+
0=
b10 ;
0G
0M
#93000000
0#
0+
#93500000
1#
1+
b11 ;
#94000000
0#
0+
#94500000
1#
1+
b100 ;
#95000000
0#
0+
#95500000
1%
1#
1-
1+
1<
b101 ;
1F
1M
1J
b0 ;
#96000000
0#
0+
#96500000
1#
1+
1=
0F
0M
0J
#97000000
0#
0+
#97500000
1#
1+
b1 ;
#98000000
0#
0+
#98500000
1#
1+
b10 ;
#99000000
0#
0+
#99500000
1#
1+
b11 ;
#100000000
0#
0+
#100500000
1#
1+
b100 ;
#101000000
0#
0+
#101500000
1#
1+
b101 ;
#102000000
0#
0+
#102500000
1#
1+
b110 ;
#103000000
0#
0+
#103500000
1#
1+
b111 ;
#104000000
0#
0+
#104500000
1#
1+
b1000 ;
#105000000
0#
0+
#105500000
0$
1#
0,
1+
b1001 ;
0<
0=
0B
0C
0D
0E
0?
0>
#106000000
0#
0+
#106500000
1#
1+
#107000000
0#
0+
#107500000
1#
1+
#108000000
0#
0+
#108500000
1#
1+
#109000000
0#
0+
#109500000
1#
1+
#110000000
0#
0+
#110500000
1#
1+
#111000000
0#
0+
#111500000
1#
1+
#112000000
0#
0+
#112500000
1#
1+
#113000000
0#
0+
#113500000
1#
1+
#114000000
0#
0+
#114500000
1#
1+
#115000000
0#
0+
#115500000
1$
1'
0%
1#
1,
1/
0-
1+
1B
1D
18
1H
1)
1J
b0 ;
#116000000
1%
0#
1-
0+
#116500000
1#
1+
1<
1C
1E
0H
1F
0J
1M
1J
b1 @
1>
0A
#117000000
0#
0+
#117500000
1#
1+
1=
0B
0F
0M
0J
#118000000
0#
0+
#118500000
1#
1+
0C
b1 ;
#119000000
0#
0+
#119500000
1#
1+
b10 ;
#120000000
0#
0+
#120500000
1#
1+
b11 ;
#121000000
0#
0+
#121500000
1#
1+
b100 ;
#122000000
0#
0+
#122500000
1#
1+
b101 ;
#123000000
0#
0+
#123500000
1#
1+
b110 ;
#124000000
0#
0+
#124500000
1#
1+
b111 ;
#125000000
0#
0+
#125500000
1#
1+
b1000 ;
#126000000
0#
0+
#126500000
1#
1+
b1001 ;
#127000000
0#
0+
#127500000
1#
1+
b1010 ;
1?
0>
1A
#128000000
0#
0+
#128500000
1#
1+
1B
08
1H
0)
1J
b0 ;
#129000000
0#
0+
#129500000
1#
1+
1C
0H
0J
#130000000
0#
0+
#130500000
1#
1+
#131000000
0%
0#
0-
0+
0?
#131500000
1#
1+
0<
18
1)
1G
1M
#132000000
0#
0+
#132500000
1#
1+
0=
0G
0M
#133000000
0#
0+
#133500000
1#
1+
#134000000
0#
0+
#134500000
1#
1+
#135000000
0#
0+
#135500000
1#
1+
#136000000
0#
0+
#136500000
1#
1+
#137000000
0#
0+
#137500000
1#
1+
#138000000
0#
0+
#138500000
1#
1+
#139000000
0#
0+
#139500000
1#
1+
#140000000
0#
0+
#140500000
1#
1+
#141000000
0#
0+
#141500000
1#
1+
#142000000
0#
0+
#142500000
1#
1+
#143000000
0#
0+
#143500000
1#
1+
#144000000
0#
0+
#144500000
1#
1+
#145000000
0#
0+
#145500000
1#
1+
#146000000
1%
0#
1-
0+
#146500000
1#
1+
1<
1F
1M
1J
1>
0A
#147000000
0#
0+
#147500000
1#
1+
1=
0B
0F
0M
0J
#148000000
0%
0#
0-
0+
0>
1A
#148500000
1#
1+
0<
1B
0C
1H
1G
1J
1M
#149000000
0#
0+
#149500000
1#
1+
0=
1C
0H
0G
0J
0M
#150000000
1%
0#
1-
0+
#150500000
1#
1+
1<
1F
1M
1J
1>
0A
#151000000
0#
0+
#151500000
1#
1+
1=
0B
0F
0M
0J
#152000000
0%
0#
0-
0+
0>
1A
#152500000
1#
1+
0<
1B
0C
1H
1G
1J
1M
#153000000
0#
0+
#153500000
1#
1+
0=
1C
0H
0G
0J
0M
#154000000
0#
0+
#154500000
1#
1+
#155000000
0#
0+
#155500000
1#
1+
#156000000
0#
0+
#156500000
1#
1+
#157000000
0#
0+
#157500000
1#
1+
#158000000
0#
0+
#158500000
1#
1+
#159000000
0#
0+
#159500000
1#
1+
#160000000
0#
0+
#160500000
1#
1+
#161000000
0#
0+
#161500000
1#
1+
#162000000
0#
0+
#162500000
1#
1+
#163000000
0#
0+
#163500000
1#
1+
#164000000
0#
0+
#164500000
1#
1+
#165000000
0#
0+
#165500000
1#
1+
#166000000
0#
0+
#166500000
1#
1+
#167000000
0#
0+
#167500000
1#
1+
#168000000
0#
0+
#168500000
1#
1+
#169000000
0#
0+
#169500000
1#
1+
#170000000
0#
0+
#170500000
1#
1+
#171000000
0#
0+
#171500000
1#
1+
#172000000
1%
0#
1-
0+
#172500000
1#
1+
1<
1F
1M
1J
1>
0A
#173000000
0#
0+
#173500000
1#
1+
1=
0B
0F
0M
0J
#174000000
0#
0+
#174500000
1#
1+
0C
b1 ;
#175000000
0#
0+
#175500000
1#
1+
b10 ;
#176000000
0#
0+
#176500000
1#
1+
b11 ;
#177000000
0#
0+
#177500000
1#
1+
b100 ;
#178000000
0#
0+
#178500000
1#
1+
b101 ;
#179000000
0#
0+
#179500000
1#
1+
b110 ;
#180000000
0#
0+
#180500000
1#
1+
b111 ;
#181000000
0#
0+
#181500000
1#
1+
b1000 ;
#182000000
0#
0+
#182500000
1#
1+
b1001 ;
#183000000
0#
0+
#183500000
1#
1+
b1010 ;
1?
0>
1A
#184000000
0#
0+
#184500000
1#
1+
1B
08
1H
0)
1J
b0 ;
#185000000
0#
0+
#185500000
1#
1+
1C
0H
0J
#186000000
0#
0+
#186500000
1#
1+
#187000000
0#
0+
#187500000
1#
1+
#188000000
0#
0+
#188500000
1#
1+
#189000000
0#
0+
#189500000
1#
1+
#190000000
0#
0+
#190500000
1#
1+
#191000000
0#
0+
#191500000
1#
1+
#192000000
0#
0+
#192500000
1#
1+
#193000000
0#
0+
#193500000
1#
1+
#194000000
0#
0+
#194500000
1#
1+
#195000000
0#
0+
#195500000
1#
1+
#196000000
0#
0+
#196500000
1#
1+
#197000000
0#
0+
#197500000
1#
1+
#198000000
0#
0+
#198500000
1#
1+
#199000000
0#
0+
#199500000
1#
1+
#200000000
0#
0+
#200500000
1#
1+
#201000000
0#
0+
#201500000
1#
1+
#202000000
0%
0#
0-
0+
0?
#202500000
1#
1+
0<
18
1)
1G
1M
#203000000
0#
0+
#203500000
1#
1+
0=
0G
0M
#204000000
1%
0#
1-
0+
#204500000
1#
1+
1<
1F
1M
1J
1>
0A
#205000000
0#
0+
#205500000
1#
1+
1=
0B
0F
0M
0J
#206000000
0%
0#
0-
0+
0>
1A
#206500000
1#
1+
0<
1B
0C
1H
1G
1J
1M
#207000000
0#
0+
#207500000
1#
1+
0=
1C
0H
0G
0J
0M
#208000000
0#
0+
#208500000
1#
1+
#209000000
0#
0+
#209500000
1#
1+
#210000000
1%
0#
1-
0+
#210500000
1#
1+
1<
1F
1M
1J
1>
0A
#211000000
0#
0+
#211500000
1#
1+
1=
0B
0F
0M
0J
#212000000
0#
0+
#212500000
1#
1+
0C
b1 ;
#213000000
0#
0+
#213500000
1#
1+
b10 ;
#214000000
0#
0+
#214500000
1#
1+
b11 ;
#215000000
0#
0+
#215500000
1#
1+
b100 ;
#216000000
0#
0+
#216500000
1#
1+
b101 ;
#217000000
0#
0+
#217500000
1#
1+
b110 ;
#218000000
0#
0+
#218500000
1#
1+
b111 ;
#219000000
0#
0+
#219500000
1#
1+
b1000 ;
#220000000
0$
0#
0,
0+
0<
0=
0D
0E
0>
1A
08
0)
#220500000
1#
1+
#221000000
0#
0+
#221500000
1#
1+
#222000000
0#
0+
#222500000
1#
1+
#223000000
0#
0+
#223500000
1#
1+
#224000000
0#
0+
#224500000
1#
1+
#225000000
0#
0+
#225500000
1#
1+
#226000000
0#
0+
#226500000
1#
1+
#227000000
0#
0+
#227500000
1#
1+
#228000000
0#
0+
#228500000
1#
1+
#229000000
0#
0+
#229500000
1#
1+
#230000000
1$
1&
0'
0%
0#
1,
1.
0/
0-
0+
#230500000
1%
1#
1-
1+
1<
1B
1D
18
1H
1)
1F
1J
1M
b10 @
b0 ;
1?
#231000000
0#
0+
#231500000
1#
1+
1=
1C
1E
08
0H
0)
0F
0M
0J
#232000000
0#
0+
#232500000
1#
1+
#233000000
0#
0+
#233500000
1#
1+
#234000000
0#
0+
#234500000
1#
1+
#235000000
0#
0+
#235500000
1#
1+
#236000000
0#
0+
#236500000
1#
1+
#237000000
0#
0+
#237500000
1#
1+
#238000000
0#
0+
#238500000
1#
1+
#239000000
0#
0+
#239500000
1#
1+
#240000000
0#
0+
#240500000
1#
1+
#241000000
0#
0+
#241500000
1#
1+
#242000000
0#
0+
#242500000
1#
1+
#243000000
0#
0+
#243500000
1#
1+
#244000000
0#
0+
#244500000
1#
1+
#245000000
0#
0+
#245500000
0%
1#
0-
1+
0<
1G
1M
1>
0A
#246000000
0#
0+
#246500000
1#
1+
0=
0B
b1 ;
0G
0M
#247000000
0#
0+
#247500000
1#
1+
0C
b10 ;
#248000000
0#
0+
#248500000
1#
1+
b11 ;
#249000000
0#
0+
#249500000
1#
1+
b100 ;
#250000000
0#
0+
#250500000
1#
1+
b101 ;
#251000000
0#
0+
#251500000
1#
1+
b110 ;
#252000000
0#
0+
#252500000
1#
1+
b111 ;
#253000000
0#
0+
#253500000
1#
1+
b1000 ;
#254000000
0#
0+
#254500000
1#
1+
b1001 ;
#255000000
0#
0+
#255500000
1#
1+
b1010 ;
0?
0>
1A
#256000000
0#
0+
#256500000
1#
1+
1B
18
1H
1)
1J
b0 ;
#257000000
0#
0+
#257500000
1#
1+
1C
0H
0J
#258000000
0#
0+
#258500000
1#
1+
#259000000
0#
0+
#259500000
1#
1+
#260000000
0#
0+
#260500000
1%
1#
1-
1+
1<
1?
1F
1M
1J
#261000000
0#
0+
#261500000
1#
1+
1=
08
0)
0F
0M
0J
#262000000
0#
0+
#262500000
0%
1#
0-
1+
0<
1G
1M
1>
0A
#263000000
0#
0+
#263500000
1#
1+
0=
0B
b1 ;
0G
0M
#264000000
0#
0+
#264500000
1%
1#
1-
1+
1<
0C
b10 ;
1F
1M
1J
b0 ;
#265000000
0#
0+
#265500000
1#
1+
1=
0F
0M
0J
#266000000
0#
0+
#266500000
0%
1#
0-
1+
0<
b1 ;
1G
1M
#267000000
0#
0+
#267500000
1#
1+
0=
b10 ;
0G
0M
#268000000
0#
0+
#268500000
1#
1+
b11 ;
#269000000
0#
0+
#269500000
1#
1+
b100 ;
#270000000
0#
0+
#270500000
1#
1+
b101 ;
#271000000
0#
0+
#271500000
1#
1+
b110 ;
#272000000
0#
0+
#272500000
1#
1+
b111 ;
#273000000
0#
0+
#273500000
1#
1+
b1000 ;
#274000000
0#
0+
#274500000
1#
1+
b1001 ;
#275000000
0#
0+
#275500000
1#
1+
b1010 ;
0?
0>
1A
#276000000
0#
0+
#276500000
1#
1+
1B
18
1H
1)
1J
b0 ;
#277000000
0#
0+
#277500000
1#
1+
1C
0H
0J
#278000000
0#
0+
#278500000
1#
1+
#279000000
0#
0+
#279500000
1#
1+
#280000000
0#
0+
#280500000
1#
1+
#281000000
0#
0+
#281500000
1#
1+
#282000000
0#
0+
#282500000
1#
1+
#283000000
0#
0+
#283500000
1#
1+
#284000000
0#
0+
#284500000
1#
1+
#285000000
0#
0+
#285500000
1#
1+
#286000000
0#
0+
#286500000
1%
1#
1-
1+
1<
1?
1F
1M
1J
#287000000
0#
0+
#287500000
1#
1+
1=
08
0)
0F
0M
0J
