MIPS_Processor/alu_unit.sv
/*
    Sub module - ALU Unit for MIPS Processor

    Operations:
    -- Add                 - alu_out = A + B
    -- Subtract            - alu_out = A - B
    -- Multiply            - alu_out = A * B
    -- Divide              - alu_out = A / B
    -- Logical Left Shift  - alu_out = A logical shifted left by 1
    -- Logical Right Shift - alu_out = A logical shifted right by 1
    -- Rotate Left         - alu_out = A rotated left by 1
    -- Rotate Right        - alu_out = A rotated right by 1
    -- Logical AND         - alu_out = A AND B
    -- Logical OR          - alu_out = A OR B
    -- Logical XOR         - alu_out = A XOR B
    -- Logical NOR         - alu_out = A NOr B
    -- Logical NAND        - alu_out = A NAND B
    -- Logical XNOR        - alu_out = A XNOR B
    -- Greater Compare     - alu_out = 1 if A > B else 0
    -- Equal Compare       - alu_out = 1 if A == B else 0
*/
module alu_unit #(
    parameter int ALU_SIZE  = 8,
    parameter int SHIFT_BIT = 1
) (
    input [ALU_SIZE-1:0] alu_in_a,
    input [ALU_SIZE-1:0] alu_in_b,
    input [3:0]          alu_sel,

    output [ALU_SIZE-1:0] alu_out,

    output carry_out
);
    wire [ALU_SIZE-1:0] alu_result;
    wire [ALU_SIZE:0]   carry_out_temp;

    always_comb begin
        case (alu_sel)
            4'b0000: alu_result = alu_in_a + alu_in_b;                            // Addition
            4'b0001: alu_result = alu_in_a - alu_in_b;                            // Subtraction
            4'b0010: alu_result = $unsigned(alu_in_a) * $unsigned(alu_in_b);      // Multiplication
            4'b0011: alu_result = $unsigned(alu_in_a) / $unsigned(alu_in_b);      // Division
            4'b0100: alu_result = alu_in_a << SHIFT_BIT;                          // Logical shift left
            4'b0101: alu_result = alu_in_a >> SHIFT_BIT;                          // Logical shift right
            4'b0110: alu_result = {alu_in_a[ALU_SIZE-2:0], alu_in_a[ALU_SIZE-1]}; // Rotate left
            4'b0111: alu_result = {alu_in_a[0], alu_in_a[ALU_SIZE-1:1]};          // Rotate right
            4'b1000: alu_result = alu_in_a & alu_in_b;                            // Logical AND
            4'b1001: alu_result = alu_in_a | alu_in_b;                            // Logical OR
            4'b1010: alu_result = alu_in_a ^ alu_in_b;                            // Logical XOR
            4'b1011: alu_result = ~(alu_in_a | alu_in_b);                         // Logical NOR
            4'b1100: alu_result = ~(alu_in_a & alu_in_b);                         // Logical NAND
            4'b1101: alu_result = ~(alu_in_a ^ alu_in_b);                         // Logical XNOR
            4'b1110: alu_result = (alu_in_a > alu_in_b) ? 'd1 : 'd0;              // Greater comparison
            4'b1111: alu_result = (alu_in_a == alu_in_b) ? 'd1 : 'd0;             // Equal comparison
            default: alu_result = alu_in_a + alu_in_b;                            // Default
        endcase
    end

    assign alu_out        = alu_result;
    assign carry_out_temp = {1'b0, alu_in_a} + {1'b0, alu_in_b};
    assign carry_out      = carry_out_temp[ALU_SIZE];
endmodule

Deafeatured/MIPS_Processor/alu_unit_tb.sv
`timescale 1ns/1ps

module alu_unit_tb #(
    parameter int ALU_SIZE = 8
) ();
    integer i;

    reg [ALU_SIZE-1:0] alu_in_a, alu_in_b;
    reg [3:0]          alu_sel;

    wire [ALU_SIZE-1:0] alu_out;

    wire carry_out;

    alu_unit #(
        .ALU_SIZE  (ALU_SIZE),
        .SHIFT_BIT (1)
    ) u_alu_unit (
        .alu_in_a  (alu_in_a),
        .alu_in_b  (alu_in_b),
        .alu_sel   (alu_sel),
        .alu_out   (alu_out),
        .carry_out (carry_out)
    );

    initial begin
        $display("ALU Unit TB");

        $dumpfile("alu_unit.vcd");
        $dumpvars();

        alu_in_a = 8'h0A;
        alu_in_b = 4'h02;
        alu_sel  = 4'h0;

        for (i = 0; i < 16; i++) begin
            alu_sel = alu_sel + 1;
            #10;
        end

    alu_in_a = 8'hF6;
    alu_in_b = 8'h0A;
    end

endmodule

Deafeatured/MIPS_Processor/alu_unit.vcd
$date
	Mon Aug 12 22:23:20 2024
$end
$version
	ModelSim Version 10.5b
$end
$timescale
	1ps
$end

$scope module alu_unit_tb $end
$var parameter 32 ! ALU_SIZE $end
$var integer 32 " i $end
$var reg 8 # alu_in_a [7:0] $end
$var reg 8 $ alu_in_b [7:0] $end
$var reg 4 % alu_sel [3:0] $end
$var wire 1 & alu_out [7] $end
$var wire 1 ' alu_out [6] $end
$var wire 1 ( alu_out [5] $end
$var wire 1 ) alu_out [4] $end
$var wire 1 * alu_out [3] $end
$var wire 1 + alu_out [2] $end
$var wire 1 , alu_out [1] $end
$var wire 1 - alu_out [0] $end
$var wire 1 . carry_out $end

$scope module u_alu_unit $end
$var parameter 32 / ALU_SIZE $end
$var parameter 32 0 SHIFT_BIT $end
$var wire 1 1 alu_in_a [7] $end
$var wire 1 2 alu_in_a [6] $end
$var wire 1 3 alu_in_a [5] $end
$var wire 1 4 alu_in_a [4] $end
$var wire 1 5 alu_in_a [3] $end
$var wire 1 6 alu_in_a [2] $end
$var wire 1 7 alu_in_a [1] $end
$var wire 1 8 alu_in_a [0] $end
$var wire 1 9 alu_in_b [7] $end
$var wire 1 : alu_in_b [6] $end
$var wire 1 ; alu_in_b [5] $end
$var wire 1 < alu_in_b [4] $end
$var wire 1 = alu_in_b [3] $end
$var wire 1 > alu_in_b [2] $end
$var wire 1 ? alu_in_b [1] $end
$var wire 1 @ alu_in_b [0] $end
$var wire 1 A alu_sel [3] $end
$var wire 1 B alu_sel [2] $end
$var wire 1 C alu_sel [1] $end
$var wire 1 D alu_sel [0] $end
$var wire 1 & alu_out [7] $end
$var wire 1 ' alu_out [6] $end
$var wire 1 ( alu_out [5] $end
$var wire 1 ) alu_out [4] $end
$var wire 1 * alu_out [3] $end
$var wire 1 + alu_out [2] $end
$var wire 1 , alu_out [1] $end
$var wire 1 - alu_out [0] $end
$var wire 1 . carry_out $end
$var reg 8 E alu_result [7:0] $end
$var wire 1 F carry_out_temp [8] $end
$var wire 1 G carry_out_temp [7] $end
$var wire 1 H carry_out_temp [6] $end
$var wire 1 I carry_out_temp [5] $end
$var wire 1 J carry_out_temp [4] $end
$var wire 1 K carry_out_temp [3] $end
$var wire 1 L carry_out_temp [2] $end
$var wire 1 M carry_out_temp [1] $end
$var wire 1 N carry_out_temp [0] $end
$upscope $end
$upscope $end

$scope begin std $end
$upscope $end
$enddefinitions $end
#0
$dumpvars
b1010 #
b10 $
b1 %
b1000 E
b1000 !
b1000 /
b1 0
b0 "
0-
0,
0+
1*
0)
0(
0'
0&
0.
0N
0M
1L
1K
0J
0I
0H
0G
0F
08
17
06
15
04
03
02
01
0@
1?
0>
0=
0<
0;
0:
09
1D
0C
0B
0A
$end
#10000
b1 "
b10 %
0D
1C
b10100 E
1+
0*
1)
#20000
b10 "
b11 %
1D
b101 E
1-
0)
#30000
b11 "
b100 %
0D
0C
1B
b10100 E
0-
1)
#40000
b100 "
b101 %
1D
b101 E
1-
0)
#50000
b101 "
b110 %
0D
1C
b10100 E
0-
1)
#60000
b110 "
b111 %
1D
b101 E
1-
0)
#70000
b111 "
b1000 %
0D
0C
0B
1A
b10 E
0-
1,
0+
#80000
b1000 "
b1001 %
1D
b1010 E
1*
#90000
b1001 "
b1010 %
0D
1C
b1000 E
0,
#100000
b1010 "
b1011 %
1D
b11110101 E
1-
1+
0*
1)
1(
1'
1&
#110000
b1011 "
b1100 %
0D
0C
1B
b11111101 E
1*
#120000
b1100 "
b1101 %
1D
b11110111 E
1,
0*
#130000
b1101 "
b1110 %
0D
1C
b1 E
0,
0+
0)
0(
0'
0&
#140000
b1110 "
b1111 %
1D
b0 E
0-
#150000
b1111 "
b0 %
0D
0C
0B
0A
b1100 E
1+
1*
#160000
b10000 "
b11110110 #
b1010 $
16
05
14
13
12
11
0L
1J
1I
1H
1G
1=
0K
0J
0I
0H
0G
1F
1.
b0 E
0+
0*
