Digital_Timer/digit_iter.sv
module digit_iter #(
    parameter int HR_DIGIT     = 0,
    parameter int MIN_DIGIT    = 0,
    parameter int SEC_DIGIT    = 0,
    parameter int FIRST_DIGIT  = 0,
    parameter int SECOND_DIGIT = 0
) (
    input timer_clk,
    input int_reset_b,

    input hr_digit_cap_in,            //! Input to indicate Hour 2nd digit == 2, used by Hour 1st digit

    input [4:0] prev_overflow_ind,

    input [6:0] clock_digit_in,

    output reg hr_digit_cap_out,      //! Output to indicate Hour 2nd digit == 2, used by Hour 1st digit

    output reg [6:0] clock_digit_out,

    output reg overflow_ind
);

    parameter int HR_FIRST_DIGIT   = HR_DIGIT && FIRST_DIGIT;
    parameter int HR_SECOND_DIGIT  = HR_DIGIT && SECOND_DIGIT;
    parameter int MIN_FIRST_DIGIT  = MIN_DIGIT && FIRST_DIGIT;
    parameter int MIN_SECOND_DIGIT = MIN_DIGIT && SECOND_DIGIT;
    parameter int SEC_FIRST_DIGIT  = SEC_DIGIT && FIRST_DIGIT;
    parameter int SEC_SECOND_DIGIT = SEC_DIGIT && SECOND_DIGIT;

    wire prev_overflow_ind_merge      = & prev_overflow_ind;

    always @(posedge timer_clk or negedge int_reset_b) begin: overflow_ind_block
        if (~int_reset_b) begin
            overflow_ind <= 0;
        end else begin
            if (SEC_DIGIT || MIN_DIGIT) begin: sec_min_digit_block
                if (FIRST_DIGIT && clock_digit_in == 7'b0010100) begin
                    overflow_ind <= 1;
                end else if (SECOND_DIGIT && clock_digit_in == 7'b0110100) begin
                    overflow_ind <= 1;
                end else begin
                    overflow_ind <= 0;
                end
            end else if (HR_DIGIT) begin: hr_digit_block
                if (FIRST_DIGIT && clock_digit_in == 7'b0010100) begin
                    overflow_ind <= 1;
                end else if (SECOND_DIGIT && clock_digit_in == 7'b0010010) begin
                    overflow_ind <= 1;
                end else begin
                    overflow_ind <= 0;
                end
            end else begin
                overflow_ind <= 0;
            end
        end
    end

    always @(posedge timer_clk or negedge int_reset_b) begin
        if (~int_reset_b) begin
            clock_digit_out <= 7'b0000001; // 0
        end else begin
            if (prev_overflow_ind_merge) begin
                if (SEC_FIRST_DIGIT || MIN_FIRST_DIGIT) begin
                    case(clock_digit_in)
                        7'b0000001: clock_digit_out <= 7'b1001111; // 0 -> 1
                        7'b1001111: clock_digit_out <= 7'b0010010; // 1 -> 2
                        7'b0010010: clock_digit_out <= 7'b0000110; // 2 -> 3
                        7'b0000110: clock_digit_out <= 7'b1011100; // 3 -> 4
                        7'b1011100: clock_digit_out <= 7'b0110100; // 4 -> 5
                        7'b0110100: clock_digit_out <= 7'b0110000; // 5 -> 6
                        7'b0110000: clock_digit_out <= 7'b0001111; // 6 -> 7
                        7'b0001111: clock_digit_out <= 7'b0010000; // 7 -> 8
                        7'b0010000: clock_digit_out <= 7'b0010100; // 8 -> 9
                        7'b0010100: clock_digit_out <= 7'b0000001; // 9 -> 0
                        default: clock_digit_out <= 7'b0000001; // 0
                    endcase
                end else if (SEC_SECOND_DIGIT || MIN_SECOND_DIGIT) begin
                    case(clock_digit_in)
                        7'b0000001: clock_digit_out <= 7'b1001111; // 0 -> 1
                        7'b1001111: clock_digit_out <= 7'b0010010; // 1 -> 2
                        7'b0010010: clock_digit_out <= 7'b0000110; // 2 -> 3
                        7'b0000110: clock_digit_out <= 7'b1011100; // 3 -> 4
                        7'b1011100: clock_digit_out <= 7'b0110100; // 4 -> 5
                        7'b0110100: clock_digit_out <= 7'b0000001; // 5 -> 0
                        default: clock_digit_out <= 7'b0000001; // 0
                    endcase
                end else if (HR_FIRST_DIGIT) begin
                    if (hr_digit_cap_out) begin
                        case(clock_digit_in)
                            7'b0000001: clock_digit_out <= 7'b1001111; // 0 -> 1
                            7'b1001111: clock_digit_out <= 7'b0010010; // 1 -> 2
                            7'b0010010: clock_digit_out <= 7'b0000110; // 2 -> 3
                            7'b0000110: clock_digit_out <= 7'b0000001; // 3 -> 0
                            default: clock_digit_out <= 7'b0000001; // 0
                        endcase
                    end else begin
                        case(clock_digit_in)
                            7'b0000001: clock_digit_out <= 7'b1001111; // 0 -> 1
                            7'b1001111: clock_digit_out <= 7'b0010010; // 1 -> 2
                            7'b0010010: clock_digit_out <= 7'b0000110; // 2 -> 3
                            7'b0000110: clock_digit_out <= 7'b1011100; // 3 -> 4
                            7'b1011100: clock_digit_out <= 7'b0110100; // 4 -> 5
                            7'b0110100: clock_digit_out <= 7'b0110000; // 5 -> 6
                            7'b0110000: clock_digit_out <= 7'b0001111; // 6 -> 7
                            7'b0001111: clock_digit_out <= 7'b0010000; // 7 -> 8
                            7'b0010000: clock_digit_out <= 7'b0010100; // 8 -> 9
                            7'b0010100: clock_digit_out <= 7'b0000001; // 9 -> 0
                            default: clock_digit_out <= 7'b0000001; // 0
                        endcase
                    end
                end else if (HR_SECOND_DIGIT) begin
                    case(clock_digit_in)
                        7'b0000001: clock_digit_out <= 7'b1001111; // 0 -> 1
                        7'b1001111: clock_digit_out <= 7'b0010010; // 1 -> 2
                        7'b0010010: clock_digit_out <= 7'b0000001; // 2 -> 0
                        default: clock_digit_out <= 7'b0000001; // 0
                    endcase
                end
            end
        end
    end

    always @(posedge timer_clk or negedge int_reset_b) begin
        if (~int_reset_b) begin
            hr_digit_cap_out <= 1'b0;
        end else begin
            if (HR_SECOND_DIGIT && clock_digit_out == 7'b0010010) begin
                hr_digit_cap_out <= 1'b1;
            end else begin
                hr_digit_cap_out <= 1'b0;
            end
        end
    end

endmodule

Digital_Timer/timer_clk_gen.sv
// Clock divider by 10
module timer_clk_gen #(
    parameter int TIMER_LIMIT = 10
) (
    input sys_clk,
    input int_reset_b,

    input timer_clear,
    input timer_pause,

    input [3:0] timer_clk_count,

    output reg timer_clk
);

    always @(posedge sys_clk or negedge int_reset_b) begin: timer_clk_gen
        if (~int_reset_b) begin
            timer_clk <= 1'b0;
        end else begin
            if (timer_clear) begin
                timer_clk <= 1'b0;
            end else if (timer_pause) begin
                timer_clk <= timer_clk;
            end else if (timer_clk_count == TIMER_LIMIT-1) begin
                timer_clk <= ~timer_clk;
            end else begin
                timer_clk <= timer_clk;
            end
        end
    end

endmodule

Digital_Timer/timer_clk_counter.sv
// Count system clock tick from 0-9
module timer_clk_counter #(
    parameter int TIMER_LIMIT = 10
) (
    input sys_clk,
    input int_reset_b,

    input timer_pause,
    input timer_clear,

    output reg [3:0] timer_clk_count
);

    always @(posedge sys_clk or negedge int_reset_b) begin: timer_clk_count_iter
        if (~int_reset_b) begin
            timer_clk_count <= 4'b0;
        end else begin
            if (timer_pause) begin
                timer_clk_count <= timer_clk_count;
            end else if (timer_clear) begin
                timer_clk_count <= 4'b0;
            end else if (timer_clk_count == TIMER_LIMIT-1) begin
                timer_clk_count <= 4'd0;
            end else begin
                timer_clk_count <= timer_clk_count + 1'b1;
            end
        end
    end

endmodule

Digital_Timer/digital_timer.sv
// Main module
module digital_timer #(
    parameter int TIMER_LIMIT = 10
) (
    input sys_clk,
    input rst_b,

    input timer_clear,
    input timer_pause,
    input timer_reset,

    output reg [5:0] [6:0] digital_clock_out
);

    reg digital_sec_2nd_ind;
    reg digital_min_2nd_ind;
    reg digital_hr_2nd_ind;

    reg digital_min_1st_ind;
    reg digital_hr_1st_ind;

    reg timer_clk;

    reg hr_digit_cap_out;

    reg [3:0] timer_clk_count;

    reg [5:0] [6:0] digital_clock_in;

    reg [1:0] hour_digit_overflow;
    reg [1:0] min_digit_overflow;
    reg [1:0] sec_digit_overflow;

    wire int_reset_b     = ~timer_reset && rst_b;
    wire hr_digit_cap_in = hr_digit_cap_out;

    // System clock tick count
    timer_clk_counter #(
        .TIMER_LIMIT (TIMER_LIMIT)
    ) u_timer_clk_counter (
        .sys_clk         (sys_clk),
        .int_reset_b     (int_reset_b),
        .timer_pause     (timer_pause),
        .timer_clear     (timer_clear),
        .timer_clk_count (timer_clk_count)
    );

    // Divide system clock by 10 to produce timer clock
    timer_clk_gen #(
        .TIMER_LIMIT (TIMER_LIMIT)
    ) u_timer_clk_gen (
        .sys_clk         (sys_clk),
        .int_reset_b     (int_reset_b),
        .timer_clear     (timer_clear),
        .timer_pause     (timer_pause),
        .timer_clk_count (timer_clk_count),
        .timer_clk       (timer_clk)
    );

    always @(posedge sys_clk or negedge int_reset_b) begin
        if (~int_reset_b) begin
            digital_clock_in <= {(6){7'b0000001}}; // Reset to 0
        end else begin
            digital_clock_in <= digital_clock_out;
        end
    end

    generate
        genvar iter;
        for (iter = 0; iter < 6; iter++) begin: gen_digital_display_iter
            case(iter)
                0: digit_iter #(
                        .HR_DIGIT     (0),
                        .MIN_DIGIT    (0),
                        .SEC_DIGIT    (1),
                        .FIRST_DIGIT  (1),
                        .SECOND_DIGIT (0)
                ) u_sec_first_digit_iter (
                        .timer_clk         (timer_clk),
                        .int_reset_b       (int_reset_b),
                        .clock_digit_in    (digital_clock_in[iter]),
                        .clock_digit_out   (digital_clock_out[iter]),
                        .hr_digit_cap_in   (1'b0),
                        .hr_digit_cap_out  (),
                        .prev_overflow_ind (5'b11111),
                        .overflow_ind      (sec_digit_overflow[0])
                    );
                1: digit_iter #(
                        .HR_DIGIT     (0),
                        .MIN_DIGIT    (0),
                        .SEC_DIGIT    (1),
                        .FIRST_DIGIT  (0),
                        .SECOND_DIGIT (1)
                ) u_sec_second_digit_iter (
                        .timer_clk         (timer_clk),
                        .int_reset_b       (int_reset_b),
                        .clock_digit_in    (digital_clock_in[iter]),
                        .clock_digit_out   (digital_clock_out[iter]),
                        .hr_digit_cap_in   (1'b0),
                        .hr_digit_cap_out  (),
                        .prev_overflow_ind ({sec_digit_overflow[0], 4'b1111}),
                        .overflow_ind      (sec_digit_overflow[1])
                    );
                2: digit_iter #(
                        .HR_DIGIT     (0),
                        .MIN_DIGIT    (1),
                        .SEC_DIGIT    (0),
                        .FIRST_DIGIT  (1),
                        .SECOND_DIGIT (0)
                ) u_min_first_digit_iter (
                        .timer_clk         (timer_clk),
                        .int_reset_b       (int_reset_b),
                        .clock_digit_in    (digital_clock_in[iter]),
                        .clock_digit_out   (digital_clock_out[iter]),
                        .hr_digit_cap_in   (1'b0),
                        .hr_digit_cap_out  (),
                        .prev_overflow_ind ({sec_digit_overflow, 3'b111}),
                        .overflow_ind      (min_digit_overflow[0])
                    );
                3: digit_iter #(
                        .HR_DIGIT     (0),
                        .MIN_DIGIT    (1),
                        .SEC_DIGIT    (0),
                        .FIRST_DIGIT  (0),
                        .SECOND_DIGIT (1)
                ) u_min_second_digit_iter (
                        .timer_clk         (timer_clk),
                        .int_reset_b       (int_reset_b),
                        .clock_digit_in    (digital_clock_in[iter]),
                        .clock_digit_out   (digital_clock_out[iter]),
                        .hr_digit_cap_in   (1'b0),
                        .hr_digit_cap_out  (),
                        .prev_overflow_ind ({min_digit_overflow[0], sec_digit_overflow, 2'b11}),
                        .overflow_ind      (min_digit_overflow[1])
                    );
                4: digit_iter #(
                        .HR_DIGIT     (1),
                        .MIN_DIGIT    (0),
                        .SEC_DIGIT    (0),
                        .FIRST_DIGIT  (1),
                        .SECOND_DIGIT (0)
                ) u_hr_first_digit_iter (
                        .timer_clk         (timer_clk),
                        .int_reset_b       (int_reset_b),
                        .clock_digit_in    (digital_clock_in[iter]),
                        .clock_digit_out   (digital_clock_out[iter]),
                        .hr_digit_cap_in   (hr_digit_cap_in),
                        .hr_digit_cap_out  (),
                        .prev_overflow_ind ({min_digit_overflow, sec_digit_overflow, 1'b1}),
                        .overflow_ind      (hour_digit_overflow[0])
                    );
                5: digit_iter #(
                        .HR_DIGIT     (1),
                        .MIN_DIGIT    (0),
                        .SEC_DIGIT    (0),
                        .FIRST_DIGIT  (0),
                        .SECOND_DIGIT (1)
                ) u_hr_second_digit_iter (
                        .timer_clk         (timer_clk),
                        .int_reset_b       (int_reset_b),
                        .clock_digit_in    (digital_clock_in[iter]),
                        .clock_digit_out   (digital_clock_out[iter]),
                        .hr_digit_cap_in   (1'b0),
                        .hr_digit_cap_out  (hr_digit_cap_out),
                        .prev_overflow_ind ({hour_digit_overflow[0], min_digit_overflow, sec_digit_overflow}),
                        .overflow_ind      (hour_digit_overflow[1])
                    );
            endcase
        end
    endgenerate

endmodule

Digital_Timer/digital_timer_tb.sv
`timescale 10ps/10ps

`define DELAY 10

module digital_timer_tb#()();

    parameter int ENDTIME    = 200000;
    parameter int TIMER_LIMIT = 4;

    reg clk;
    reg rst_b;

    reg timer_clear;
    reg timer_pause;
    reg timer_reset;

    reg [5:0] [6:0] digital_clock;

    digital_timer #(
        .TIMER_LIMIT (TIMER_LIMIT)
    ) u_dut (
        .sys_clk           (clk),
        .rst_b             (rst_b),
        .timer_clear       (timer_clear),
        .timer_pause       (timer_pause),
        .timer_reset       (timer_reset),
        .digital_clock_out (digital_clock)
    );

    initial begin
        $display("Digital Timer TB");

        $dumpfile("digital_timer.vcd");
        $dumpvars();

        clk         = 1'b0;
        rst_b       = 1'b0;
        timer_clear = 1'b0;
        timer_pause = 1'b0;
        timer_reset = 1'b0;
    end

    initial begin
        main;
    end

    task static main;
        fork
            clock_gen;
            reset_gen;
            operation_process;
            endsimulation;
        join
    endtask

    task static clock_gen;
        begin
            forever #`DELAY clk = ~clk;
        end
    endtask

    task static reset_gen;
        begin
            #(`DELAY*2)
            rst_b = 1'b1;
            # 20
            rst_b = 1'b0;
            # 25
            rst_b = 1'b1;
        end
    endtask

    task static operation_process;
        begin
            // Set timer_pause and release to test timer pause function
            #(`DELAY*25)
            timer_pause = 1'b1;
            #(`DELAY*10)
            timer_pause = 1'b0;

            // Set timer_clear and release to test timer clear function
            #(`DELAY*38)
            timer_clear = 1'b1;
            #(`DELAY*5)
            timer_clear = 1'b0;

            // Set timer_reset and release to test timer reset function
            #(`DELAY*50)
            timer_reset = 1'b1;
            #(`DELAY*6)
            timer_reset = 1'b0;

            //forever #`DELAY $display("%d", digital_clock);
        end
    endtask

    task static endsimulation;
        begin
            #ENDTIME
            $display("---------------- THE SIMULATION HAS FINISHED -----------------");
            $finish;
        end
    endtask

endmodule

Digital_Timer/vcd/digital_timer.vcd
$date
	Thu Aug 29 21:03:14 2024
$end
$version
	ModelSim Version 10.5b
$end
$timescale
	10ps
$end

$scope module digital_timer_tb $end
$var parameter 32 ! ENDTIME $end
$var parameter 32 " TIMER_LIMIT $end
$var reg 1 # clk $end
$var reg 1 $ rst_b $end
$var reg 1 % timer_clear $end
$var reg 1 & timer_pause $end
$var reg 1 ' timer_reset $end
$var reg 42 ( digital_clock [41:0] $end

$scope task main $end
$upscope $end

$scope task clock_gen $end
$upscope $end

$scope task reset_gen $end
$upscope $end

$scope task operation_process $end
$upscope $end

$scope task endsimulation $end
$upscope $end

$scope module u_dut $end
$var parameter 32 ) TIMER_LIMIT $end
$var wire 1 * sys_clk $end
$var wire 1 + rst_b $end
$var wire 1 , timer_clear $end
$var wire 1 - timer_pause $end
$var wire 1 . timer_reset $end
$var reg 42 / digital_clock_out [41:0] $end
$var reg 1 0 digital_sec_2nd_ind $end
$var reg 1 1 digital_min_2nd_ind $end
$var reg 1 2 digital_hr_2nd_ind $end
$var reg 1 3 digital_min_1st_ind $end
$var reg 1 4 digital_hr_1st_ind $end
$var reg 1 5 timer_clk $end
$var reg 1 6 hr_digit_cap_out $end
$var reg 4 7 timer_clk_count [3:0] $end
$var reg 42 8 digital_clock_in [41:0] $end
$var reg 2 9 hour_digit_overflow [1:0] $end
$var reg 2 : min_digit_overflow [1:0] $end
$var reg 2 ; sec_digit_overflow [1:0] $end
$var wire 1 < int_reset_b $end
$var wire 1 = hr_digit_cap_in $end

$scope begin gen_digital_display_iter[5] $end
$var parameter 32 > iter $end

$scope begin genblk1 $end

$scope module u_hr_second_digit_iter $end
$var parameter 32 ? HR_DIGIT $end
$var parameter 32 @ MIN_DIGIT $end
$var parameter 32 A SEC_DIGIT $end
$var parameter 32 B FIRST_DIGIT $end
$var parameter 32 C SECOND_DIGIT $end
$var parameter 32 D HR_FIRST_DIGIT $end
$var parameter 32 E HR_SECOND_DIGIT $end
$var parameter 32 F MIN_FIRST_DIGIT $end
$var parameter 32 G MIN_SECOND_DIGIT $end
$var parameter 32 H SEC_FIRST_DIGIT $end
$var parameter 32 I SEC_SECOND_DIGIT $end
$var wire 1 J timer_clk $end
$var wire 1 < int_reset_b $end
$var wire 1 K hr_digit_cap_in $end
$var wire 1 L prev_overflow_ind [4] $end
$var wire 1 M prev_overflow_ind [3] $end
$var wire 1 N prev_overflow_ind [2] $end
$var wire 1 O prev_overflow_ind [1] $end
$var wire 1 P prev_overflow_ind [0] $end
$var wire 1 Q clock_digit_in [6] $end
$var wire 1 R clock_digit_in [5] $end
$var wire 1 S clock_digit_in [4] $end
$var wire 1 T clock_digit_in [3] $end
$var wire 1 U clock_digit_in [2] $end
$var wire 1 V clock_digit_in [1] $end
$var wire 1 W clock_digit_in [0] $end
$var reg 1 X hr_digit_cap_out $end
$var reg 7 Y clock_digit_out [6:0] $end
$var reg 1 Z overflow_ind $end
$var wire 1 [ prev_overflow_ind_merge $end

$scope begin overflow_ind_block $end

$scope begin sec_min_digit_block $end
$upscope $end

$scope begin hr_digit_block $end
$upscope $end
$upscope $end
$upscope $end
$upscope $end
$upscope $end

$scope begin gen_digital_display_iter[4] $end
$var parameter 32 \ iter $end

$scope begin genblk1 $end

$scope module u_hr_first_digit_iter $end
$var parameter 32 ] HR_DIGIT $end
$var parameter 32 ^ MIN_DIGIT $end
$var parameter 32 _ SEC_DIGIT $end
$var parameter 32 ` FIRST_DIGIT $end
$var parameter 32 a SECOND_DIGIT $end
$var parameter 32 b HR_FIRST_DIGIT $end
$var parameter 32 c HR_SECOND_DIGIT $end
$var parameter 32 d MIN_FIRST_DIGIT $end
$var parameter 32 e MIN_SECOND_DIGIT $end
$var parameter 32 f SEC_FIRST_DIGIT $end
$var parameter 32 g SEC_SECOND_DIGIT $end
$var wire 1 h timer_clk $end
$var wire 1 < int_reset_b $end
$var wire 1 = hr_digit_cap_in $end
$var wire 1 i prev_overflow_ind [4] $end
$var wire 1 j prev_overflow_ind [3] $end
$var wire 1 k prev_overflow_ind [2] $end
$var wire 1 l prev_overflow_ind [1] $end
$var wire 1 m prev_overflow_ind [0] $end
$var wire 1 n clock_digit_in [6] $end
$var wire 1 o clock_digit_in [5] $end
$var wire 1 p clock_digit_in [4] $end
$var wire 1 q clock_digit_in [3] $end
$var wire 1 r clock_digit_in [2] $end
$var wire 1 s clock_digit_in [1] $end
$var wire 1 t clock_digit_in [0] $end
$var reg 1 u hr_digit_cap_out $end
$var reg 7 v clock_digit_out [6:0] $end
$var reg 1 w overflow_ind $end
$var wire 1 x prev_overflow_ind_merge $end

$scope begin overflow_ind_block $end

$scope begin sec_min_digit_block $end
$upscope $end

$scope begin hr_digit_block $end
$upscope $end
$upscope $end
$upscope $end
$upscope $end
$upscope $end

$scope begin gen_digital_display_iter[3] $end
$var parameter 32 y iter $end

$scope begin genblk1 $end

$scope module u_min_second_digit_iter $end
$var parameter 32 z HR_DIGIT $end
$var parameter 32 { MIN_DIGIT $end
$var parameter 32 | SEC_DIGIT $end
$var parameter 32 } FIRST_DIGIT $end
$var parameter 32 ~ SECOND_DIGIT $end
$var parameter 32 !! HR_FIRST_DIGIT $end
$var parameter 32 "! HR_SECOND_DIGIT $end
$var parameter 32 #! MIN_FIRST_DIGIT $end
$var parameter 32 $! MIN_SECOND_DIGIT $end
$var parameter 32 %! SEC_FIRST_DIGIT $end
$var parameter 32 &! SEC_SECOND_DIGIT $end
$var wire 1 '! timer_clk $end
$var wire 1 < int_reset_b $end
$var wire 1 (! hr_digit_cap_in $end
$var wire 1 )! prev_overflow_ind [4] $end
$var wire 1 *! prev_overflow_ind [3] $end
$var wire 1 +! prev_overflow_ind [2] $end
$var wire 1 ,! prev_overflow_ind [1] $end
$var wire 1 -! prev_overflow_ind [0] $end
$var wire 1 .! clock_digit_in [6] $end
$var wire 1 /! clock_digit_in [5] $end
$var wire 1 0! clock_digit_in [4] $end
$var wire 1 1! clock_digit_in [3] $end
$var wire 1 2! clock_digit_in [2] $end
$var wire 1 3! clock_digit_in [1] $end
$var wire 1 4! clock_digit_in [0] $end
$var reg 1 5! hr_digit_cap_out $end
$var reg 7 6! clock_digit_out [6:0] $end
$var reg 1 7! overflow_ind $end
$var wire 1 8! prev_overflow_ind_merge $end

$scope begin overflow_ind_block $end

$scope begin sec_min_digit_block $end
$upscope $end

$scope begin hr_digit_block $end
$upscope $end
$upscope $end
$upscope $end
$upscope $end
$upscope $end

$scope begin gen_digital_display_iter[2] $end
$var parameter 32 9! iter $end

$scope begin genblk1 $end

$scope module u_min_first_digit_iter $end
$var parameter 32 :! HR_DIGIT $end
$var parameter 32 ;! MIN_DIGIT $end
$var parameter 32 <! SEC_DIGIT $end
$var parameter 32 =! FIRST_DIGIT $end
$var parameter 32 >! SECOND_DIGIT $end
$var parameter 32 ?! HR_FIRST_DIGIT $end
$var parameter 32 @! HR_SECOND_DIGIT $end
$var parameter 32 A! MIN_FIRST_DIGIT $end
$var parameter 32 B! MIN_SECOND_DIGIT $end
$var parameter 32 C! SEC_FIRST_DIGIT $end
$var parameter 32 D! SEC_SECOND_DIGIT $end
$var wire 1 E! timer_clk $end
$var wire 1 < int_reset_b $end
$var wire 1 F! hr_digit_cap_in $end
$var wire 1 G! prev_overflow_ind [4] $end
$var wire 1 H! prev_overflow_ind [3] $end
$var wire 1 I! prev_overflow_ind [2] $end
$var wire 1 J! prev_overflow_ind [1] $end
$var wire 1 K! prev_overflow_ind [0] $end
$var wire 1 L! clock_digit_in [6] $end
$var wire 1 M! clock_digit_in [5] $end
$var wire 1 N! clock_digit_in [4] $end
$var wire 1 O! clock_digit_in [3] $end
$var wire 1 P! clock_digit_in [2] $end
$var wire 1 Q! clock_digit_in [1] $end
$var wire 1 R! clock_digit_in [0] $end
$var reg 1 S! hr_digit_cap_out $end
$var reg 7 T! clock_digit_out [6:0] $end
$var reg 1 U! overflow_ind $end
$var wire 1 V! prev_overflow_ind_merge $end

$scope begin overflow_ind_block $end

$scope begin sec_min_digit_block $end
$upscope $end

$scope begin hr_digit_block $end
$upscope $end
$upscope $end
$upscope $end
$upscope $end
$upscope $end

$scope begin gen_digital_display_iter[1] $end
$var parameter 32 W! iter $end

$scope begin genblk1 $end

$scope module u_sec_second_digit_iter $end
$var parameter 32 X! HR_DIGIT $end
$var parameter 32 Y! MIN_DIGIT $end
$var parameter 32 Z! SEC_DIGIT $end
$var parameter 32 [! FIRST_DIGIT $end
$var parameter 32 \! SECOND_DIGIT $end
$var parameter 32 ]! HR_FIRST_DIGIT $end
$var parameter 32 ^! HR_SECOND_DIGIT $end
$var parameter 32 _! MIN_FIRST_DIGIT $end
$var parameter 32 `! MIN_SECOND_DIGIT $end
$var parameter 32 a! SEC_FIRST_DIGIT $end
$var parameter 32 b! SEC_SECOND_DIGIT $end
$var wire 1 c! timer_clk $end
$var wire 1 < int_reset_b $end
$var wire 1 d! hr_digit_cap_in $end
$var wire 1 e! prev_overflow_ind [4] $end
$var wire 1 f! prev_overflow_ind [3] $end
$var wire 1 g! prev_overflow_ind [2] $end
$var wire 1 h! prev_overflow_ind [1] $end
$var wire 1 i! prev_overflow_ind [0] $end
$var wire 1 j! clock_digit_in [6] $end
$var wire 1 k! clock_digit_in [5] $end
$var wire 1 l! clock_digit_in [4] $end
$var wire 1 m! clock_digit_in [3] $end
$var wire 1 n! clock_digit_in [2] $end
$var wire 1 o! clock_digit_in [1] $end
$var wire 1 p! clock_digit_in [0] $end
$var reg 1 q! hr_digit_cap_out $end
$var reg 7 r! clock_digit_out [6:0] $end
$var reg 1 s! overflow_ind $end
$var wire 1 t! prev_overflow_ind_merge $end

$scope begin overflow_ind_block $end

$scope begin sec_min_digit_block $end
$upscope $end

$scope begin hr_digit_block $end
$upscope $end
$upscope $end
$upscope $end
$upscope $end
$upscope $end

$scope begin gen_digital_display_iter[0] $end
$var parameter 32 u! iter $end

$scope begin genblk1 $end

$scope module u_sec_first_digit_iter $end
$var parameter 32 v! HR_DIGIT $end
$var parameter 32 w! MIN_DIGIT $end
$var parameter 32 x! SEC_DIGIT $end
$var parameter 32 y! FIRST_DIGIT $end
$var parameter 32 z! SECOND_DIGIT $end
$var parameter 32 {! HR_FIRST_DIGIT $end
$var parameter 32 |! HR_SECOND_DIGIT $end
$var parameter 32 }! MIN_FIRST_DIGIT $end
$var parameter 32 ~! MIN_SECOND_DIGIT $end
$var parameter 32 !" SEC_FIRST_DIGIT $end
$var parameter 32 "" SEC_SECOND_DIGIT $end
$var wire 1 #" timer_clk $end
$var wire 1 < int_reset_b $end
$var wire 1 $" hr_digit_cap_in $end
$var wire 1 %" prev_overflow_ind [4] $end
$var wire 1 &" prev_overflow_ind [3] $end
$var wire 1 '" prev_overflow_ind [2] $end
$var wire 1 (" prev_overflow_ind [1] $end
$var wire 1 )" prev_overflow_ind [0] $end
$var wire 1 *" clock_digit_in [6] $end
$var wire 1 +" clock_digit_in [5] $end
$var wire 1 ," clock_digit_in [4] $end
$var wire 1 -" clock_digit_in [3] $end
$var wire 1 ." clock_digit_in [2] $end
$var wire 1 /" clock_digit_in [1] $end
$var wire 1 0" clock_digit_in [0] $end
$var reg 1 1" hr_digit_cap_out $end
$var reg 7 2" clock_digit_out [6:0] $end
$var reg 1 3" overflow_ind $end
$var wire 1 4" prev_overflow_ind_merge $end

$scope begin overflow_ind_block $end

$scope begin sec_min_digit_block $end
$upscope $end

$scope begin hr_digit_block $end
$upscope $end
$upscope $end
$upscope $end
$upscope $end
$upscope $end

$scope module u_timer_clk_counter $end
$var parameter 32 5" TIMER_LIMIT $end
$var wire 1 * sys_clk $end
$var wire 1 < int_reset_b $end
$var wire 1 - timer_pause $end
$var wire 1 , timer_clear $end
$var reg 4 6" timer_clk_count [3:0] $end

$scope begin timer_clk_count_iter $end
$upscope $end
$upscope $end

$scope module u_timer_clk_gen $end
$var parameter 32 7" TIMER_LIMIT $end
$var wire 1 * sys_clk $end
$var wire 1 < int_reset_b $end
$var wire 1 , timer_clear $end
$var wire 1 - timer_pause $end
$var wire 1 8" timer_clk_count [3] $end
$var wire 1 9" timer_clk_count [2] $end
$var wire 1 :" timer_clk_count [1] $end
$var wire 1 ;" timer_clk_count [0] $end
$var reg 1 <" timer_clk $end

$scope begin timer_clk_gen $end
$upscope $end
$upscope $end
$upscope $end
$upscope $end

$scope begin std $end
$upscope $end
$enddefinitions $end
#0
$dumpvars
0#
0$
0%
0&
0'
b100000010000001000000100000010000001 (
b100000010000001000000100000010000001 /
x0
x1
x2
x3
x4
05
06
b0 7
b100000010000001000000100000010000001 8
b0 9
b0 :
b0 ;
b0 6"
0<"
01"
b1 2"
03"
0q!
b1 r!
0s!
0S!
b1 T!
0U!
05!
b1 6!
07!
0u
b1 v
0w
0X
b1 Y
0Z
b110000110101000000 !
b100 "
b100 )
b100 5"
b100 7"
b0 u!
b0 v!
b0 w!
b1 x!
b1 y!
b0 z!
b0 {!
b0 |!
b0 }!
b0 ~!
b1 !"
b0 ""
b1 W!
b0 X!
b0 Y!
b1 Z!
b0 [!
b1 \!
b0 ]!
b0 ^!
b0 _!
b0 `!
b0 a!
b1 b!
b10 9!
b0 :!
b1 ;!
b0 <!
b1 =!
b0 >!
b0 ?!
b0 @!
b1 A!
b0 B!
b0 C!
b0 D!
b11 y
b0 z
b1 {
b0 |
b0 }
b1 ~
b0 !!
b0 "!
b0 #!
b1 $!
b0 %!
b0 &!
b100 \
b1 ]
b0 ^
b0 _
b1 `
b0 a
b1 b
b0 c
b0 d
b0 e
b0 f
b0 g
b101 >
b1 ?
b0 @
b0 A
b0 B
b1 C
b0 D
b1 E
b0 F
b0 G
b0 H
b0 I
0<
0=
14"
0t!
0V!
08!
0x
0[
0*
0+
0,
0-
0.
1)"
1("
1'"
1&"
1%"
0$"
0e!
1i!
1h!
1g!
1f!
0d!
0H!
0G!
1K!
1J!
1I!
0F!
0)!
0+!
0*!
1-!
1,!
0(!
0j
0i
0l
0k
1m
0K
0;"
0:"
09"
08"
0#"
10"
0/"
0."
0-"
0,"
0+"
0*"
0c!
1p!
0o!
0n!
0m!
0l!
0k!
0j!
0E!
1R!
0Q!
0P!
0O!
0N!
0M!
0L!
0'!
14!
03!
02!
01!
00!
0/!
0.!
0h
1t
0s
0r
0q
0p
0o
0n
0J
1W
0V
0U
0T
0S
0R
0Q
0P
0O
0N
0M
0L
$end
#10
1#
1*
#20
1$
0#
1+
0*
1<
#30
1#
1*
b1 6"
b1 7
1;"
#40
0$
0#
0+
0*
0<
b0 6"
b0 7
0;"
#50
1#
1*
#60
0#
0*
#65
1$
1+
1<
#70
1#
1*
b1 6"
b1 7
1;"
#80
0#
0*
#90
1#
1*
b10 6"
b10 7
0;"
1:"
#100
0#
0*
#110
1#
1*
b11 6"
b11 7
1;"
#120
0#
0*
#130
1#
1*
b0 6"
1<"
15
b0 7
0;"
0:"
1J
1h
1'!
1E!
1c!
1#"
b1001111 2"
b100000010000001000000100000011001111 /
b100000010000001000000100000011001111 (
#140
0#
0*
#150
1#
1*
b1 6"
b100000010000001000000100000011001111 8
b1 7
1;"
1/"
1."
1-"
1*"
#160
0#
0*
#170
1#
1*
b10 6"
b10 7
0;"
1:"
#180
0#
0*
#190
1#
1*
b11 6"
b11 7
1;"
#200
0#
0*
#210
1#
1*
b0 6"
0<"
05
b0 7
0;"
0:"
0J
0h
0'!
0E!
0c!
0#"
#220
0#
0*
#230
1#
1*
b1 6"
b1 7
1;"
#240
0#
0*
#250
1&
1#
1-
1*
#260
0#
0*
#270
1#
1*
#280
0#
0*
#290
1#
1*
#300
0#
0*
#310
1#
1*
#320
0#
0*
#330
1#
1*
#340
0#
0*
