Digital_Timer/digit_iter.sv
module digit_iter #(
    parameter int HR_DIGIT     = 0,
    parameter int MIN_DIGIT    = 0,
    parameter int SEC_DIGIT    = 0,
    parameter int FIRST_DIGIT  = 0,
    parameter int SECOND_DIGIT = 0
) (
    input timer_clk,
    input int_reset_b,

    input [4:0] prev_overflow_ind,

    input [6:0] clock_digit_in,

    output reg [6:0] clock_digit_out,

    output reg overflow_ind
);
    wire prev_overflow_ind_merge = & prev_overflow_ind;

    always @(posedge timer_clk or negedge int_reset_b) begin
        if (~int_reset_b) begin
            overflow_ind <= 0;
        end else begin
            if (SEC_DIGIT || MIN_DIGIT) begin
                if (FIRST_DIGIT && clock_digit_in == 7'b0010100) begin
                    overflow_ind <= 1;
                end else if (SECOND_DIGIT && clock_digit_in == 7'b0110100) begin
                    overflow_ind <= 1;
                end else begin
                    overflow_ind <= 0;
                end
            end else if (HR_DIGIT) begin
                if (FIRST_DIGIT && clock_digit_in == 7'b0010100) begin
                    overflow_ind <= 1;
                end else if (SECOND_DIGIT && clock_digit_in == 7'b0010010) begin
                    overflow_ind <= 1;
                end else begin
                    overflow_ind <= 0;
                end
            end else begin
                overflow_ind <= 0;
            end
        end
    end

    always @(posedge timer_clk or negedge int_reset_b) begin
        if (~int_reset_b) begin
            clock_digit_out <= 7'b0000001; // 0
        end else begin
            if (prev_overflow_ind_merge) begin
                case(clock_digit_in)
                    7'b0000001: clock_digit_out <= 7'b1001111; // 0 -> 1
                    7'b1001111: clock_digit_out <= 7'b0010010; // 1 -> 2
                    7'b0010010: clock_digit_out <= 7'b0000110; // 2 -> 3
                    7'b0000110: clock_digit_out <= 7'b1011100; // 3 -> 4
                    7'b1011100: clock_digit_out <= 7'b0110100; // 4 -> 5
                    7'b0110100: clock_digit_out <= 7'b0110000; // 5 -> 6
                    7'b0110000: clock_digit_out <= 7'b0001111; // 6 -> 7
                    7'b0001111: clock_digit_out <= 7'b0010000; // 7 -> 8
                    7'b0010000: clock_digit_out <= 7'b0010100; // 8 -> 9
                    7'b0010100: clock_digit_out <= 7'b0000001; // 9 -> 0
                    default: clock_digit_out <= 7'b0000001; // 0
                endcase
            end
        end
    end

endmodule

Digital_Timer/timer_clk_gen.sv
// Clock divider by 10
module timer_clk_gen #() (
    input sys_clk,
    input int_reset_b,

    input timer_clear,
    input timer_pause,

    input [3:0] timer_clk_count,

    output reg timer_clk
);

    always @(posedge sys_clk or negedge int_reset_b) begin: timer_clk_gen
        if (~int_reset_b) begin
            timer_clk <= 1'b0;
        end else begin
            if (timer_clear) begin
                timer_clk <= 1'b0;
            end else if (timer_pause) begin
                timer_clk <= timer_clk;
            end else if (timer_clk_count == 'd9) begin
                timer_clk <= ~timer_clk;
            end else begin
                timer_clk <= timer_clk;
            end
        end
    end

endmodule

Digital_Timer/timer_clk_counter.sv
// Count system clock tick from 0-9
module timer_clk_counter #() (
    input sys_clk,
    input int_reset_b,

    input timer_pause,
    input timer_clear,

    output reg [3:0] timer_clk_count
);

    always @(posedge sys_clk or negedge int_reset_b) begin: timer_clk_count_iter
        if (~int_reset_b) begin
            timer_clk_count <= 4'b0;
        end else begin
            if (timer_pause) begin
                timer_clk_count <= timer_clk_count;
            end else if (timer_clear) begin
                timer_clk_count <= 4'b0;
            end else if (timer_clk_count == 'd9) begin
                timer_clk_count <= 4'd0;
            end else begin
                timer_clk_count <= timer_clk_count + 1'b1;
            end
        end
    end

endmodule

Digital_Timer/digital_timer.sv
// Main module
module digital_timer #() (
    input sys_clk,
    input rst_b,

    input timer_clear,
    input timer_pause,
    input timer_reset,

    output reg [5:0] [6:0] digital_clock_out
);

    reg digital_sec_2nd_ind;
    reg digital_min_2nd_ind;
    reg digital_hr_2nd_ind;

    reg digital_min_1st_ind;
    reg digital_hr_1st_ind;

    reg timer_clk;

    reg [3:0] timer_clk_count;

    reg [5:0] [6:0] digital_clock_in;

    reg [1:0] hour_digit_overflow;
    reg [1:0] min_digit_overflow;
    reg [1:0] sec_digit_overflow;

    wire int_reset_b = ~timer_reset && rst_b;

    // System clock tick count
    timer_clk_counter #() u_timer_clk_counter (
        .sys_clk         (sys_clk),
        .int_reset_b     (int_reset_b),
        .timer_pause     (timer_pause),
        .timer_clear     (timer_clear),
        .timer_clk_count (timer_clk_count)
    );

    // Divide system clock by 10 to produce timer clock
    timer_clk_gen #() u_timer_clk_gen (
        .sys_clk         (sys_clk),
        .int_reset_b     (int_reset_b),
        .timer_clear     (timer_clear),
        .timer_pause     (timer_pause),
        .timer_clk_count (timer_clk_count),
        .timer_clk       (timer_clk)
    );

    always @(posedge sys_clk or negedge int_reset_b) begin
        if (~int_reset_b) begin
            digital_clock_in <= {(6){7'b0000001}}; // Reset to 0
        end else begin
            digital_clock_in <= digital_clock_out;
        end
    end

    generate
        genvar iter;
        for (iter = 0; iter < 6; iter++) begin: gen_digital_display_iter
            case(iter)
                0: digit_iter #(
                        .HR_DIGIT     (0),
                        .MIN_DIGIT    (0),
                        .SEC_DIGIT    (1),
                        .FIRST_DIGIT  (1),
                        .SECOND_DIGIT (0)
                ) u_sec_first_digit_iter (
                        .timer_clk         (timer_clk),
                        .int_reset_b       (int_reset_b),
                        .clock_digit_in    (digital_clock_in[iter]),
                        .clock_digit_out   (digital_clock_out[iter]),
                        .prev_overflow_ind (5'b11111),
                        .overflow_ind      (sec_digit_overflow[0])
                    );
                1: digit_iter #(
                        .HR_DIGIT     (0),
                        .MIN_DIGIT    (0),
                        .SEC_DIGIT    (1),
                        .FIRST_DIGIT  (0),
                        .SECOND_DIGIT (1)
                ) u_sec_second_digit_iter (
                        .timer_clk         (timer_clk),
                        .int_reset_b       (int_reset_b),
                        .clock_digit_in    (digital_clock_in[iter]),
                        .clock_digit_out   (digital_clock_out[iter]),
                        .prev_overflow_ind ({sec_digit_overflow[0], 4'b1111}),
                        .overflow_ind      (sec_digit_overflow[1])
                    );
                2: digit_iter #(
                        .HR_DIGIT     (0),
                        .MIN_DIGIT    (1),
                        .SEC_DIGIT    (0),
                        .FIRST_DIGIT  (1),
                        .SECOND_DIGIT (0)
                ) u_min_first_digit_iter (
                        .timer_clk         (timer_clk),
                        .int_reset_b       (int_reset_b),
                        .clock_digit_in    (digital_clock_in[iter]),
                        .clock_digit_out   (digital_clock_out[iter]),
                        .prev_overflow_ind ({sec_digit_overflow, 3'b111}),
                        .overflow_ind      (min_digit_overflow[0])
                    );
                3: digit_iter #(
                        .HR_DIGIT     (0),
                        .MIN_DIGIT    (1),
                        .SEC_DIGIT    (0),
                        .FIRST_DIGIT  (0),
                        .SECOND_DIGIT (1)
                ) u_min_second_digit_iter (
                        .timer_clk         (timer_clk),
                        .int_reset_b       (int_reset_b),
                        .clock_digit_in    (digital_clock_in[iter]),
                        .clock_digit_out   (digital_clock_out[iter]),
                        .prev_overflow_ind ({min_digit_overflow[0], sec_digit_overflow, 2'b11}),
                        .overflow_ind      (min_digit_overflow[1])
                    );
                4: digit_iter #(
                        .HR_DIGIT     (1),
                        .MIN_DIGIT    (0),
                        .SEC_DIGIT    (0),
                        .FIRST_DIGIT  (1),
                        .SECOND_DIGIT (0)
                ) u_hr_first_digit_iter (
                        .timer_clk         (timer_clk),
                        .int_reset_b       (int_reset_b),
                        .clock_digit_in    (digital_clock_in[iter]),
                        .clock_digit_out   (digital_clock_out[iter]),
                        .prev_overflow_ind ({min_digit_overflow, sec_digit_overflow, 1'b1}),
                        .overflow_ind      (hour_digit_overflow[0])
                    );
                5: digit_iter #(
                        .HR_DIGIT     (1),
                        .MIN_DIGIT    (0),
                        .SEC_DIGIT    (0),
                        .FIRST_DIGIT  (0),
                        .SECOND_DIGIT (1)
                ) u_hr_second_digit_iter (
                        .timer_clk         (timer_clk),
                        .int_reset_b       (int_reset_b),
                        .clock_digit_in    (digital_clock_in[iter]),
                        .clock_digit_out   (digital_clock_out[iter]),
                        .prev_overflow_ind ({hour_digit_overflow[0], min_digit_overflow, sec_digit_overflow}),
                        .overflow_ind      (hour_digit_overflow[1])
                    );
            endcase
        end
    endgenerate

endmodule

Digital_Timer/digital_timer_tb.sv
`timescale 10ps/10ps

`define DELAY 10

module digital_timer_tb#()();

    parameter int ENDTIME = 2000;

    reg clk;
    reg rst_b;

    reg timer_clear;
    reg timer_pause;
    reg timer_reset;

    reg [5:0] [6:0] digital_clock;

    digital_timer #() u_dut (
        .sys_clk           (clk),
        .rst_b             (rst_b),
        .timer_clear       (timer_clear),
        .timer_pause       (timer_pause),
        .timer_reset       (timer_reset),
        .digital_clock_out (digital_clock)
    );

    initial begin
        $display("Digital Timer TB");

        $dumpfile("digital_timer.vcd");
        $dumpvars();

        clk         = 1'b0;
        rst_b       = 1'b0;
        timer_clear = 1'b0;
        timer_pause = 1'b0;
        timer_reset = 1'b0;
    end

    initial begin
        main;
    end

    task static main;
        fork
            clock_gen;
            reset_gen;
            operation_process;
            endsimulation;
        join
    endtask

    task static clock_gen;
        begin
            forever #`DELAY clk = ~clk;
        end
    endtask

    task static reset_gen;
        begin
            #(`DELAY*2)
            rst_b = 1'b1;
            # 20
            rst_b = 1'b0;
            # 25
            rst_b = 1'b1;
        end
    endtask

    task static operation_process;
        begin
            forever #`DELAY $display("%d", digital_clock);
        end
    endtask

    task static endsimulation;
        begin
            #ENDTIME
            $display("---------------- THE SIMULATION HAS FINISHED -----------------");
            $finish;
        end
    endtask

endmodule

Digital_Timer/vcd/digital_timer.vcd
$date
	Wed Aug 28 23:35:27 2024
$end
$version
	ModelSim Version 10.5b
$end
$timescale
	10ps
$end

$scope module digital_timer_tb $end
$var parameter 32 ! ENDTIME $end
$var reg 1 " clk $end
$var reg 1 # rst_b $end
$var reg 1 $ timer_clear $end
$var reg 1 % timer_pause $end
$var reg 1 & timer_reset $end
$var reg 42 ' digital_clock [41:0] $end

$scope task main $end
$upscope $end

$scope task clock_gen $end
$upscope $end

$scope task reset_gen $end
$upscope $end

$scope task operation_process $end
$upscope $end

$scope task endsimulation $end
$upscope $end

$scope module u_dut $end
$var wire 1 ( sys_clk $end
$var wire 1 ) rst_b $end
$var wire 1 * timer_clear $end
$var wire 1 + timer_pause $end
$var wire 1 , timer_reset $end
$var reg 42 - digital_clock_out [41:0] $end
$var reg 1 . digital_sec_2nd_ind $end
$var reg 1 / digital_min_2nd_ind $end
$var reg 1 0 digital_hr_2nd_ind $end
$var reg 1 1 digital_min_1st_ind $end
$var reg 1 2 digital_hr_1st_ind $end
$var reg 1 3 timer_clk $end
$var reg 4 4 timer_clk_count [3:0] $end
$var reg 42 5 digital_clock_in [41:0] $end
$var reg 2 6 hour_digit_overflow [1:0] $end
$var reg 2 7 min_digit_overflow [1:0] $end
$var reg 2 8 sec_digit_overflow [1:0] $end
$var wire 1 9 int_reset_b $end

$scope begin gen_digital_display_iter[5] $end
$var parameter 32 : iter $end

$scope begin genblk1 $end

$scope module u_hr_second_digit_iter $end
$var parameter 32 ; HR_DIGIT $end
$var parameter 32 < MIN_DIGIT $end
$var parameter 32 = SEC_DIGIT $end
$var parameter 32 > FIRST_DIGIT $end
$var parameter 32 ? SECOND_DIGIT $end
$var wire 1 @ timer_clk $end
$var wire 1 9 int_reset_b $end
$var wire 1 A prev_overflow_ind [4] $end
$var wire 1 B prev_overflow_ind [3] $end
$var wire 1 C prev_overflow_ind [2] $end
$var wire 1 D prev_overflow_ind [1] $end
$var wire 1 E prev_overflow_ind [0] $end
$var wire 1 F clock_digit_in [6] $end
$var wire 1 G clock_digit_in [5] $end
$var wire 1 H clock_digit_in [4] $end
$var wire 1 I clock_digit_in [3] $end
$var wire 1 J clock_digit_in [2] $end
$var wire 1 K clock_digit_in [1] $end
$var wire 1 L clock_digit_in [0] $end
$var reg 7 M clock_digit_out [6:0] $end
$var reg 1 N overflow_ind $end
$var wire 1 O prev_overflow_ind_merge $end
$upscope $end
$upscope $end
$upscope $end

$scope begin gen_digital_display_iter[4] $end
$var parameter 32 P iter $end

$scope begin genblk1 $end

$scope module u_hr_first_digit_iter $end
$var parameter 32 Q HR_DIGIT $end
$var parameter 32 R MIN_DIGIT $end
$var parameter 32 S SEC_DIGIT $end
$var parameter 32 T FIRST_DIGIT $end
$var parameter 32 U SECOND_DIGIT $end
$var wire 1 V timer_clk $end
$var wire 1 9 int_reset_b $end
$var wire 1 W prev_overflow_ind [4] $end
$var wire 1 X prev_overflow_ind [3] $end
$var wire 1 Y prev_overflow_ind [2] $end
$var wire 1 Z prev_overflow_ind [1] $end
$var wire 1 [ prev_overflow_ind [0] $end
$var wire 1 \ clock_digit_in [6] $end
$var wire 1 ] clock_digit_in [5] $end
$var wire 1 ^ clock_digit_in [4] $end
$var wire 1 _ clock_digit_in [3] $end
$var wire 1 ` clock_digit_in [2] $end
$var wire 1 a clock_digit_in [1] $end
$var wire 1 b clock_digit_in [0] $end
$var reg 7 c clock_digit_out [6:0] $end
$var reg 1 d overflow_ind $end
$var wire 1 e prev_overflow_ind_merge $end
$upscope $end
$upscope $end
$upscope $end

$scope begin gen_digital_display_iter[3] $end
$var parameter 32 f iter $end

$scope begin genblk1 $end

$scope module u_min_second_digit_iter $end
$var parameter 32 g HR_DIGIT $end
$var parameter 32 h MIN_DIGIT $end
$var parameter 32 i SEC_DIGIT $end
$var parameter 32 j FIRST_DIGIT $end
$var parameter 32 k SECOND_DIGIT $end
$var wire 1 l timer_clk $end
$var wire 1 9 int_reset_b $end
$var wire 1 m prev_overflow_ind [4] $end
$var wire 1 n prev_overflow_ind [3] $end
$var wire 1 o prev_overflow_ind [2] $end
$var wire 1 p prev_overflow_ind [1] $end
$var wire 1 q prev_overflow_ind [0] $end
$var wire 1 r clock_digit_in [6] $end
$var wire 1 s clock_digit_in [5] $end
$var wire 1 t clock_digit_in [4] $end
$var wire 1 u clock_digit_in [3] $end
$var wire 1 v clock_digit_in [2] $end
$var wire 1 w clock_digit_in [1] $end
$var wire 1 x clock_digit_in [0] $end
$var reg 7 y clock_digit_out [6:0] $end
$var reg 1 z overflow_ind $end
$var wire 1 { prev_overflow_ind_merge $end
$upscope $end
$upscope $end
$upscope $end

$scope begin gen_digital_display_iter[2] $end
$var parameter 32 | iter $end

$scope begin genblk1 $end

$scope module u_min_first_digit_iter $end
$var parameter 32 } HR_DIGIT $end
$var parameter 32 ~ MIN_DIGIT $end
$var parameter 32 !! SEC_DIGIT $end
$var parameter 32 "! FIRST_DIGIT $end
$var parameter 32 #! SECOND_DIGIT $end
$var wire 1 $! timer_clk $end
$var wire 1 9 int_reset_b $end
$var wire 1 %! prev_overflow_ind [4] $end
$var wire 1 &! prev_overflow_ind [3] $end
$var wire 1 '! prev_overflow_ind [2] $end
$var wire 1 (! prev_overflow_ind [1] $end
$var wire 1 )! prev_overflow_ind [0] $end
$var wire 1 *! clock_digit_in [6] $end
$var wire 1 +! clock_digit_in [5] $end
$var wire 1 ,! clock_digit_in [4] $end
$var wire 1 -! clock_digit_in [3] $end
$var wire 1 .! clock_digit_in [2] $end
$var wire 1 /! clock_digit_in [1] $end
$var wire 1 0! clock_digit_in [0] $end
$var reg 7 1! clock_digit_out [6:0] $end
$var reg 1 2! overflow_ind $end
$var wire 1 3! prev_overflow_ind_merge $end
$upscope $end
$upscope $end
$upscope $end

$scope begin gen_digital_display_iter[1] $end
$var parameter 32 4! iter $end

$scope begin genblk1 $end

$scope module u_sec_second_digit_iter $end
$var parameter 32 5! HR_DIGIT $end
$var parameter 32 6! MIN_DIGIT $end
$var parameter 32 7! SEC_DIGIT $end
$var parameter 32 8! FIRST_DIGIT $end
$var parameter 32 9! SECOND_DIGIT $end
$var wire 1 :! timer_clk $end
$var wire 1 9 int_reset_b $end
$var wire 1 ;! prev_overflow_ind [4] $end
$var wire 1 <! prev_overflow_ind [3] $end
$var wire 1 =! prev_overflow_ind [2] $end
$var wire 1 >! prev_overflow_ind [1] $end
$var wire 1 ?! prev_overflow_ind [0] $end
$var wire 1 @! clock_digit_in [6] $end
$var wire 1 A! clock_digit_in [5] $end
$var wire 1 B! clock_digit_in [4] $end
$var wire 1 C! clock_digit_in [3] $end
$var wire 1 D! clock_digit_in [2] $end
$var wire 1 E! clock_digit_in [1] $end
$var wire 1 F! clock_digit_in [0] $end
$var reg 7 G! clock_digit_out [6:0] $end
$var reg 1 H! overflow_ind $end
$var wire 1 I! prev_overflow_ind_merge $end
$upscope $end
$upscope $end
$upscope $end

$scope begin gen_digital_display_iter[0] $end
$var parameter 32 J! iter $end

$scope begin genblk1 $end

$scope module u_sec_first_digit_iter $end
$var parameter 32 K! HR_DIGIT $end
$var parameter 32 L! MIN_DIGIT $end
$var parameter 32 M! SEC_DIGIT $end
$var parameter 32 N! FIRST_DIGIT $end
$var parameter 32 O! SECOND_DIGIT $end
$var wire 1 P! timer_clk $end
$var wire 1 9 int_reset_b $end
$var wire 1 Q! prev_overflow_ind [4] $end
$var wire 1 R! prev_overflow_ind [3] $end
$var wire 1 S! prev_overflow_ind [2] $end
$var wire 1 T! prev_overflow_ind [1] $end
$var wire 1 U! prev_overflow_ind [0] $end
$var wire 1 V! clock_digit_in [6] $end
$var wire 1 W! clock_digit_in [5] $end
$var wire 1 X! clock_digit_in [4] $end
$var wire 1 Y! clock_digit_in [3] $end
$var wire 1 Z! clock_digit_in [2] $end
$var wire 1 [! clock_digit_in [1] $end
$var wire 1 \! clock_digit_in [0] $end
$var reg 7 ]! clock_digit_out [6:0] $end
$var reg 1 ^! overflow_ind $end
$var wire 1 _! prev_overflow_ind_merge $end
$upscope $end
$upscope $end
$upscope $end

$scope module u_timer_clk_counter $end
$var wire 1 ( sys_clk $end
$var wire 1 9 int_reset_b $end
$var wire 1 + timer_pause $end
$var wire 1 * timer_clear $end
$var reg 4 `! timer_clk_count [3:0] $end

$scope begin timer_clk_count_iter $end
$upscope $end
$upscope $end

$scope module u_timer_clk_gen $end
$var wire 1 ( sys_clk $end
$var wire 1 9 int_reset_b $end
$var wire 1 * timer_clear $end
$var wire 1 + timer_pause $end
$var wire 1 a! timer_clk_count [3] $end
$var wire 1 b! timer_clk_count [2] $end
$var wire 1 c! timer_clk_count [1] $end
$var wire 1 d! timer_clk_count [0] $end
$var reg 1 e! timer_clk $end

$scope begin timer_clk_gen $end
$upscope $end
$upscope $end
$upscope $end
$upscope $end

$scope begin std $end
$upscope $end
$enddefinitions $end
#0
$dumpvars
0"
0#
0$
0%
0&
b100000010000001000000100000010000001 '
b100000010000001000000100000010000001 -
x.
x/
x0
x1
x2
03
b0 4
b100000010000001000000100000010000001 5
b0 6
b0 7
b0 8
b0 `!
0e!
b1 ]!
0^!
b1 G!
0H!
b1 1!
02!
b1 y
0z
b1 c
0d
b1 M
0N
b110000110101000000 !
b0 J!
b0 K!
b0 L!
b1 M!
b1 N!
b0 O!
b1 4!
b0 5!
b0 6!
b1 7!
b0 8!
b1 9!
b10 |
b0 }
b1 ~
b0 !!
b1 "!
b0 #!
b11 f
b0 g
b1 h
b0 i
b0 j
b1 k
b100 P
b1 Q
b0 R
b0 S
b1 T
b0 U
b101 :
b1 ;
b0 <
b0 =
b0 >
b1 ?
09
1_!
0I!
03!
0{
0e
0O
0(
0)
0*
0+
0,
1U!
1T!
1S!
1R!
1Q!
0;!
1?!
1>!
1=!
1<!
0&!
0%!
1)!
1(!
1'!
0m
0o
0n
1q
1p
0X
0W
0Z
0Y
1[
0d!
0c!
0b!
0a!
0P!
1\!
0[!
0Z!
0Y!
0X!
0W!
0V!
0:!
1F!
0E!
0D!
0C!
0B!
0A!
0@!
0$!
10!
0/!
0.!
0-!
0,!
0+!
0*!
0l
1x
0w
0v
0u
0t
0s
0r
0V
1b
0a
0`
0_
0^
0]
0\
0@
1L
0K
0J
0I
0H
0G
0F
0E
0D
0C
0B
0A
$end
#10
1"
1(
#20
1#
0"
1)
0(
19
#30
1"
1(
b1 `!
b1 4
1d!
#40
0#
0"
0)
0(
09
b0 `!
b0 4
0d!
#50
1"
1(
#60
0"
0(
#65
1#
1)
19
#70
1"
1(
b1 `!
b1 4
1d!
#80
0"
0(
#90
1"
1(
b10 `!
b10 4
0d!
1c!
#100
0"
0(
#110
1"
1(
b11 `!
b11 4
1d!
#120
0"
0(
#130
1"
1(
b100 `!
b100 4
0d!
0c!
1b!
#140
0"
0(
#150
1"
1(
b101 `!
b101 4
1d!
#160
0"
0(
#170
1"
1(
b110 `!
b110 4
0d!
1c!
#180
0"
0(
#190
1"
1(
b111 `!
b111 4
1d!
#200
0"
0(
#210
1"
1(
b1000 `!
b1000 4
0d!
0c!
0b!
1a!
#220
0"
0(
#230
1"
1(
b1001 `!
b1001 4
1d!
#240
0"
0(
#250
1%
1"
1+
1(
#260
0"
0(
#270
1"
1(
#280
0"
0(
#290
1"
1(
#300
0"
0(
#310
1"
1(
#320
0"
0(
#330
1"
1(
#340
0"
0(
#350
0%
1"
0+
1(
b0 `!
1e!
13
b0 4
0d!
0a!
1@
1V
1l
1$!
1:!
1P!
b1001111 ]!
b100000010000001000000100000011001111 -
b100000010000001000000100000011001111 '
#360
0"
0(
#370
1"
1(
b1 `!
b100000010000001000000100000011001111 5
b1 4
1d!
1[!
1Z!
1Y!
1V!
#380
0"
0(
#390
1"
1(
b10 `!
b10 4
0d!
1c!
#400
0"
0(
#410
1"
1(
b11 `!
b11 4
1d!
#420
0"
0(
#430
1"
1(
b100 `!
b100 4
0d!
0c!
1b!
#440
0"
0(
#450
1"
1(
b101 `!
b101 4
1d!
#460
0"
0(
#470
1"
1(
b110 `!
b110 4
0d!
1c!
#480
0"
0(
#490
1"
1(
b111 `!
b111 4
1d!
#500
0"
0(
#510
1"
1(
b1000 `!
b1000 4
0d!
0c!
0b!
1a!
#520
0"
0(
#530
1"
1(
b1001 `!
b1001 4
1d!
#540
0"
0(
#550
1"
1(
b0 `!
0e!
03
b0 4
0d!
0a!
0@
0V
0l
0$!
0:!
0P!
#560
0"
0(
#570
1"
1(
b1 `!
b1 4
1d!
#580
0"
0(
#590
1"
1(
b10 `!
b10 4
0d!
1c!
#600
0"
0(
#610
1"
1(
b11 `!
b11 4
1d!
#620
0"
0(
#630
1"
1(
b100 `!
b100 4
0d!
0c!
1b!
#640
0"
0(
#650
1"
1(
b101 `!
b101 4
1d!
#660
0"
0(
#670
1"
1(
b110 `!
b110 4
0d!
1c!
#680
0"
0(
#690
1"
1(
b111 `!
b111 4
1d!
#700
0"
0(
#710
1"
1(
b1000 `!
b1000 4
0d!
0c!
0b!
1a!
#720
0"
0(
#730
1$
1"
1*
1(
b0 `!
b0 4
0a!
#740
0"
0(
#750
1"
1(
#760
0"
0(
#770
1"
1(
#780
0$
0"
0*
0(
#790
1"
1(
b1 `!
b1 4
1d!
#800
0"
0(
#810
1"
1(
b10 `!
b10 4
0d!
1c!
#820
0"
0(
#830
1"
1(
b11 `!
b11 4
1d!
#840
0"
0(
#850
1"
1(
b100 `!
b100 4
0d!
0c!
1b!
#860
0"
0(
#870
1"
1(
b101 `!
b101 4
1d!
#880
0"
0(
#890
1"
1(
b110 `!
b110 4
0d!
1c!
#900
0"
0(
#910
1"
1(
b111 `!
b111 4
1d!
#920
0"
0(
#930
1"
1(
b1000 `!
b1000 4
0d!
0c!
0b!
1a!
#940
0"
0(
#950
1"
1(
b1001 `!
b1001 4
1d!
#960
0"
0(
#970
1"
1(
b0 `!
1e!
13
b0 4
0d!
0a!
1@
1V
1l
1$!
1:!
1P!
b10010 ]!
b100000010000001000000100000010010010 -
b100000010000001000000100000010010010 '
#980
0"
0(
#990
1"
1(
b1 `!
b100000010000001000000100000010010010 5
b1 4
1d!
0\!
0Z!
0Y!
1X!
0V!
#1000
0"
0(
#1010
1"
1(
b10 `!
b10 4
0d!
1c!
#1020
0"
0(
#1030
1"
1(
b11 `!
b11 4
1d!
#1040
0"
0(
#1050
1"
1(
b100 `!
b100 4
0d!
0c!
1b!
#1060
0"
0(
#1070
1"
1(
b101 `!
b101 4
1d!
#1080
0"
0(
#1090
1"
1(
b110 `!
b110 4
0d!
1c!
#1100
0"
0(
#1110
1"
1(
b111 `!
b111 4
1d!
#1120
0"
0(
#1130
1"
1(
b1000 `!
b1000 4
0d!
0c!
0b!
1a!
#1140
0"
0(
#1150
1"
1(
b1001 `!
b1001 4
1d!
#1160
0"
0(
#1170
1"
1(
b0 `!
0e!
03
b0 4
0d!
0a!
0@
0V
0l
0$!
0:!
0P!
#1180
0"
0(
#1190
1"
1(
b1 `!
b1 4
1d!
#1200
0"
0(
#1210
1"
1(
b10 `!
b10 4
0d!
1c!
#1220
0"
0(
#1230
1"
1(
b11 `!
b11 4
1d!
#1240
0"
0(
#1250
1"
1(
b100 `!
b100 4
0d!
0c!
1b!
#1260
0"
0(
#1270
1"
1(
b101 `!
b101 4
1d!
#1280
1&
0"
1,
0(
09
b0 `!
b100000010000001000000100000010000001 5
b1 ]!
b100000010000001000000100000010000001 -
b0 4
b100000010000001000000100000010000001 '
0d!
0b!
1\!
0[!
0X!
#1290
1"
1(
#1300
0"
0(
#1310
1"
1(
#1320
0"
0(
#1330
1"
1(
#1340
0&
0"
0,
0(
19
#1350
1"
1(
b1 `!
b1 4
1d!
#1360
0"
0(
#1370
1"
1(
b10 `!
b10 4
0d!
1c!
#1380
0"
0(
#1390
1"
1(
b11 `!
b11 4
1d!
#1400
0"
0(
#1410
1"
1(
b100 `!
b100 4
0d!
0c!
1b!
#1420
0"
0(
#1430
1"
1(
b101 `!
b101 4
1d!
#1440
0"
0(
#1450
1"
1(
b110 `!
b110 4
0d!
1c!
#1460
0"
0(
#1470
1"
1(
b111 `!
b111 4
1d!
#1480
0"
0(
#1490
1"
1(
b1000 `!
b1000 4
0d!
0c!
0b!
1a!
#1500
0"
0(
#1510
1"
1(
b1001 `!
b1001 4
1d!
#1520
0"
0(
#1530
1"
1(
b0 `!
1e!
13
b0 4
0d!
0a!
1@
1V
1l
1$!
1:!
1P!
b1001111 ]!
b100000010000001000000100000011001111 -
b100000010000001000000100000011001111 '
#1540
0"
0(
#1550
1"
1(
b1 `!
b100000010000001000000100000011001111 5
b1 4
1d!
1[!
1Z!
1Y!
1V!
#1560
0"
0(
#1570
1"
1(
b10 `!
b10 4
0d!
1c!
#1580
0"
0(
#1590
1"
1(
b11 `!
b11 4
1d!
#1600
0"
0(
#1610
1"
1(
b100 `!
b100 4
0d!
0c!
1b!
#1620
0"
0(
#1630
1"
1(
b101 `!
b101 4
1d!
#1640
0"
0(
#1650
1"
1(
b110 `!
b110 4
0d!
1c!
#1660
0"
0(
#1670
1"
1(
b111 `!
b111 4
1d!
#1680
0"
0(
#1690
1"
1(
b1000 `!
b1000 4
0d!
0c!
0b!
1a!
#1700
0"
0(
#1710
1"
1(
b1001 `!
b1001 4
1d!
#1720
0"
0(
#1730
1"
1(
b0 `!
0e!
03
b0 4
0d!
0a!
0@
0V
0l
0$!
0:!
0P!
#1740
0"
0(
#1750
1"
1(
b1 `!
b1 4
1d!
#1760
0"
0(
#1770
1"
1(
b10 `!
b10 4
0d!
1c!
#1780
0"
0(
#1790
1"
1(
b11 `!
b11 4
1d!
#1800
0"
0(
#1810
1"
1(
b100 `!
b100 4
0d!
0c!
1b!
#1820
0"
0(
#1830
1"
1(
b101 `!
b101 4
1d!
#1840
0"
0(
#1850
1"
1(
b110 `!
b110 4
0d!
1c!
#1860
0"
0(
#1870
1"
1(
b111 `!
b111 4
1d!
#1880
0"
0(
#1890
1"
1(
b1000 `!
b1000 4
0d!
0c!
0b!
1a!
#1900
0"
0(
#1910
1"
1(
b1001 `!
b1001 4
1d!
#1920
0"
0(
#1930
1"
1(
b0 `!
1e!
13
b0 4
0d!
0a!
1@
1V
1l
1$!
1:!
1P!
b10010 ]!
b100000010000001000000100000010010010 -
b100000010000001000000100000010010010 '
#1940
0"
0(
#1950
1"
1(
b1 `!
b100000010000001000000100000010010010 5
b1 4
1d!
0\!
0Z!
0Y!
1X!
0V!
#1960
0"
0(
#1970
1"
1(
b10 `!
b10 4
0d!
1c!
#1980
0"
0(
#1990
1"
1(
b11 `!
b11 4
1d!
#2000
0"
0(
#2010
1"
1(
b100 `!
b100 4
0d!
0c!
1b!
#2020
0"
0(
#2030
1"
1(
b101 `!
b101 4
1d!
#2040
0"
0(
#2050
1"
1(
b110 `!
b110 4
0d!
1c!
#2060
0"
0(
#2070
1"
1(
b111 `!
b111 4
1d!
#2080
0"
0(
#2090
1"
1(
b1000 `!
b1000 4
0d!
0c!
0b!
1a!
#2100
0"
0(
#2110
1"
1(
b1001 `!
b1001 4
1d!
#2120
0"
0(
#2130
1"
1(
b0 `!
0e!
03
b0 4
0d!
0a!
0@
0V
0l
0$!
0:!
0P!
#2140
0"
0(
#2150
1"
1(
b1 `!
b1 4
1d!
#2160
0"
0(
#2170
1"
1(
b10 `!
b10 4
0d!
1c!
#2180
0"
0(
#2190
1"
1(
b11 `!
b11 4
1d!
#2200
0"
0(
#2210
1"
1(
b100 `!
b100 4
0d!
0c!
1b!
#2220
0"
0(
#2230
1"
1(
b101 `!
b101 4
1d!
#2240
0"
0(
#2250
1"
1(
b110 `!
b110 4
0d!
1c!
#2260
0"
0(
#2270
1"
1(
b111 `!
b111 4
1d!
#2280
0"
0(
#2290
1"
1(
b1000 `!
b1000 4
0d!
0c!
0b!
1a!
#2300
0"
0(
#2310
1"
1(
b1001 `!
b1001 4
1d!
#2320
0"
0(
#2330
1"
1(
b0 `!
1e!
13
b0 4
0d!
0a!
1@
1V
1l
1$!
1:!
1P!
b110 ]!
b100000010000001000000100000010000110 -
b100000010000001000000100000010000110 '
#2340
0"
0(
#2350
1"
1(
b1 `!
b100000010000001000000100000010000110 5
b1 4
1d!
1Z!
0X!
#2360
0"
0(
#2370
1"
1(
b10 `!
b10 4
0d!
1c!
#2380
0"
0(
#2390
1"
1(
b11 `!
b11 4
1d!
